{"edition":"almizan_ur","name":"تفسیر المیزان","author":"Allamah Muhammad Husayn Tabatabai","language":"ur","text":"# آیات\n\n```arabic\nوَإِذَا تُتْلَىٰ عَلَيْهِمْ ءَايَـٰتُنَا بَيِّنَـٰتٍ قَالَ ٱلَّذِينَ كَفَرُوا۟ لِلَّذِينَ ءَامَنُوٓا۟ أَىُّ ٱلْفَرِيقَيْنِ خَيْرٌ مَّقَامًا وَأَحْسَنُ نَدِيًّا (٧٣)\n```\n\n```urdu\nاور جب ان کے سامنے ہماری کِھلی ہوئی آیتیں پیش کی جاتی ہیں تو ان میں کے کافر صاحبان ایمان سے کہتے ہیں کہ ہم دونوں میں کس کی جگہ بہتر اور کس کی منزل زیادہ حسن ہے (۷۳)\n```\n\n```arabic\nوَكَمْ أَهْلَكْنَا قَبْلَهُم مِّن قَرْنٍ هُمْ أَحْسَنُ أَثَـٰثًا وَرِءْيًا (٧٤)\n```\n\n```urdu\nاور ہم نے ان سے پہلے کتنی ہی جماعتوں کوہلاک کُردیا ہے جو سازوسامان اور نام و نمود میں ان سے کہیں زیادہ بہتر تھے (۷۴)\n```\n\n```arabic\nقُلْ مَن كَانَ فِى ٱلضَّلَـٰلَةِ فَلْيَمْدُدْ لَهُ ٱلرَّحْمَـٰنُ مَدًّا ۚ حَتَّىٰٓ إِذَا رَأَوْا۟ مَا يُوعَدُونَ إِمَّا ٱلْعَذَابَ وَإِمَّا ٱلسَّاعَةَ فَسَيَعْلَمُونَ مَنْ هُوَ شَرٌّ مَّكَانًا وَأَضْعَفُ جُندًا (٧٥)\n```\n\n```urdu\nآپ کہہ دیجئے کہ جو شخص گمراہی میں پڑا رہے گا خدا اسے اور ڈھیل دیتا رہے گا یہاں تک کہ یہ وعدہ الٰہی کو دیکھ لیں .... یا عذاب کی یا قیامت کی شکل میں .... پھر انہیں معلوم ہوجائے گا کہ جگہ کے اعتبار سے بدترین اور مددگاروں کے اعتبار سے کمزور ترین کون ہے (۷۵)\n```\n\n```arabic\nوَيَزِيدُ ٱللَّهُ ٱلَّذِينَ ٱهْتَدَوْا۟ هُدًى ۗ وَٱلْبَـٰقِيَـٰتُ ٱلصَّـٰلِحَـٰتُ خَيْرٌ عِندَ رَبِّكَ ثَوَابًا وَخَيْرٌ مَّرَدًّا (٧٦)\n```\n\n```urdu\nاور اللہ ہدایت یافتہ افراد کی ہدایت میں اضافہ کردیتا ہے اور باقی رہنے والی نیکیاں آپ کے پروردگار کے نزدیک ثواب اور بازگشت کے اعتبار سے بہترین اور بلند ترین ہیں (۷۶)\n```\n\n```arabic\nأَفَرَءَيْتَ ٱلَّذِى كَفَرَ بِـَٔايَـٰتِنَا وَقَالَ لَأُوتَيَنَّ مَالًا وَوَلَدًا (٧٧)\n```\n\n```urdu\nکیا تم نے اس شخص کو بھی دیکھا ہے جس نے ہماری آیات کا انکار کیا اور یہ کہنے لگا کہ ہمیں قیامت میں بھی مال اور اولاد سے نوازا جائے گا (۷۷)\n```\n\n```arabic\nأَطَّلَعَ ٱلْغَيْبَ أَمِ ٱتَّخَذَ عِندَ ٱلرَّحْمَـٰنِ عَهْدًا (٧٨)\n```\n\n```urdu\nیہ غیب سے باخبر ہوگیا ہے یا اس نے رحمان سے کوئی معاہدہ کرلیا ہے (۷۸)\n```\n\n```arabic\nكَلَّا ۚ سَنَكْتُبُ مَا يَقُولُ وَنَمُدُّ لَهُۥ مِنَ ٱلْعَذَابِ مَدًّا (٧٩)\n```\n\n```urdu\nہرگز ایسا نہیں ہے ہم اس کی باتوں کو درج کررہے ہیں اور اس کے عذاب میں اور بھی اضافہ کردیں گے (۷۹)\n```\n\n```arabic\nوَنَرِثُهُۥ مَا يَقُولُ وَيَأْتِينَا فَرْدًا (٨٠)\n```\n\n```urdu\nاور اس کے مال و اولاد کے ہم ہی مالک ہوں گے اور یہ تو ہماری بارگاہ میں اکیلا حاضر ہوگا (۸۰)\n```\n\n## (تفسیر و بیان)\n\nیہ ان کے منقولہ کلمات کی دوسری فصل ہے، اور یہ ان کا نبوی دعوت کو یہ کہہ کر مسترد کرنا ہے کہ یہ دعوت اہل ایمان کے حال کو بہتر بنانے میں ذرہ برابر بھی نفع بخش نہیں ہے۔ ان کا استدلال یہ تھا کہ اگر یہ دعوت حق ہوتی تو ان کے لیے دنیاوی زندگی کی وہ رونق کھینچ لاتی جس میں بلند و بالا عمارات، نفیس ساز و سامان اور حسن و زیبائش جیسی زندگی کی سعادتیں پنہاں ہیں۔ پس وہ کفر جس پر وہ قائم ہیں اور جس نے ان کے لیے دنیا کی بھلائیاں فراہم کر دی ہیں، اس ایمان سے بہتر ہے جس پر مومنین کاربند ہیں جبکہ ان پر خستہ حالی، مال کی کمی اور معاشی تنگی چھائی ہوئی ہے۔ ان کے نزدیک ان کا کفر ہی وہ حق ہے جسے اختیار کرنا چاہیے، نہ کہ وہ ایمان جس پر مومنین ہیں۔ اللہ تعالیٰ نے ان کے اس قول کا جواب اپنے اس فرمان: **وَكَمْ أَهْلَكْنا** (اور ہم نے کتنی ہی نسلوں کو ہلاک کر دیا) الخ، اور اپنے اس فرمان: **قُلْ مَنْ كانَ فِي الضَّلالَةِ** (کہہ دیجیے کہ جو گمراہی میں ہے) الخ، سے دیا ہے، پھر اس کے بعد ان لوگوں کے حال کا بیان کیا جو ان کی باتوں سے دھوکا کھا گئے۔\n\n**اللہ تعالیٰ کا فرمان:** **وَإِذا تُتْلى عَلَيْهِمْ آياتُنا** (اور جب ان کے سامنے ہماری آیتیں پڑھی جاتی ہیں) آیت کے آخر تک۔ **المقام** قیام سے اسمِ مکان ہے، جس کے معنی رہنے کی جگہ یا مسکن کے ہیں۔ **الندي** سے مراد مجلس ہے، اور بعض نے کہا ہے کہ اس سے مراد خاص طور پر مشاورتی مجلس ہے۔ **قالَ الَّذِينَ كَفَرُوا لِلَّذِينَ آمَنُوا** (کافروں نے ایمان لانے والوں سے کہا) کا مطلب یہ ہے کہ انہوں نے ان سے خطاب کیا، پس یہاں \"لام\" تبلیغ کے لیے ہے جیسا کہ کہا گیا ہے۔ بعض کا قول ہے کہ یہ تعلیل کا فائدہ دیتا ہے، یعنی انہوں نے مومنین کی خاطر (انہیں گمراہ کرنے اور ایمان سے پھیرنے کے لیے) یہ بات کہی۔ تاہم پہلا معنی سیاق و سباق کے زیادہ موزوں ہے، جیسا کہ سیاق کے اعتبار سے یہ بات بھی زیادہ مناسب ہے کہ **عَلَيْهِمْ** کی ضمیر لوگوں کی طرف پلٹے جو کفار اور مومنین دونوں کو شامل ہے، نہ کہ صرف کفار کی طرف، تاکہ **قالَ الَّذِينَ كَفَرُوا** کا جملہ اسمِ ظاہر کو اسمِ ضمیر کی جگہ رکھنے کے قبیل سے ہو جائے۔\n\nاور اللہ کا فرمان: **أَيُّ الْفَرِيقَيْنِ خَيْرٌ مَقاماً وَأَحْسَنُ نَدِيًّا** (ان دونوں گروہوں میں سے کس کا مقام بہتر اور کس کی مجلس زیادہ اچھی ہے؟) یہاں **أَيُّ** استفہام کے لیے ہے اور دو گروہوں سے مراد کفار اور مومنین ہیں۔ ان کا مقصد یہ تھا کہ کفار ان مومنین سے مقام و مجلس کے اعتبار سے بہتر ہیں جن میں اکثریت غلاموں اور فقراء کی تھی، لیکن انہوں نے اس بات کو سوال کی صورت میں پیش کیا اور دونوں گروہوں کا کنایہ اس دعوے کے ساتھ کیا کہ مومنین بھی اس حقیقت سے واقف ہیں اور اگر ان سے پوچھا جائے تو وہ بغیر کسی ہچکچاہٹ اور شک کے یہی جواب دیں گے۔\n\nمعنی یہ ہے کہ: جب لوگوں پر—جو کہ دو گروہ یعنی کفار اور مومنین ہیں—ہماری آیات تلاوت کی جاتی ہیں جو اپنی حجت میں ظاہر اور اپنی دلالت میں واضح ہیں اور کسی شک کرنے والے کے لیے شک کی گنجائش نہیں چھوڑتیں، تو ان میں سے ایک گروہ یعنی کفار نے دوسرے گروہ یعنی مومنین سے کہا: ان دو گروہوں میں سے کون مسکن کے لحاظ سے بہتر اور مجلس کے اعتبار سے زیادہ اچھا ہے؟—اور یقیناً وہ کفار ہی تھے—ان کا مقصد یہ تھا کہ اس کا لازمہ یہ ہے کہ وہ اپنے طریقے اور ملت میں کامیاب و بامراد ہیں، کیونکہ دنیاوی زندگی کے ساز و سامان سے لطف اندوز ہونے کے سوا کوئی سعادت نہیں، لہٰذا حق وہی ہے جس پر وہ قائم ہیں۔\n\n**اللہ تعالیٰ کا فرمان:** **وَكَمْ أَهْلَكْنا قَبْلَهُمْ مِنْ قَرْنٍ هُمْ أَحْسَنُ أَثاثاً وَرِءْياً**\n**وَكَمْ أَهْلَكْنَا قَبْلَهُمْ مِنْ قَرْنٍ هُمْ أَحْسَنُ أَثَاثًا وَرِئْيًا**\n**اور ہم نے ان سے پہلے کتنی ہی نسلوں کو ہلاک کر دیا ہے جو ان سے بہتر سامان اور ظاہری نمود و نمائش رکھنے والے تھے۔** (سورہ مریم، آیت ۷۴)\n\n**القرن :** وہ لوگ جو ایک ہی زمانے میں اکٹھے ہوں۔ **الأثاث :** گھر کا ساز و سامان؛ کہا گیا ہے کہ اس کا اطلاق صرف کثیر سامان پر ہوتا ہے اور اس کے اپنے لفظ سے کوئی واحد نہیں ہے۔ **الرئي** (راء کے نیچے زیر اور ہمزہ ساکن): وہ مناظر جو دیکھے جائیں۔ مجمع البیان میں بعض سے نقل کیا گیا ہے کہ یہ اس چیز کا نام ہے جو ظاہر ہو، یہ مصدر نہیں ہے، کیونکہ مصدر تو \"الرأی\" اور \"الرؤیۃ\" ہے، جس کی دلیل اللہ کا یہ فرمان ہے: **يَرَوْنَهُمْ مِثْلَيْهِمْ رَأْيَ الْعَيْنِ** (وہ انہیں اپنی آنکھوں سے اپنے سے دوگنا دیکھ رہے تھے)۔ پس \"الرأی\" فعل ہے اور \"الرئی\" مرئی (دیکھی جانے والی چیز) ہے، جیسے \"الطحن\" (پیسنا) اور \"الطحن\" (پیسی ہوئی چیز)۔ (اقتباس ختم)\n\nجب کفار نے اپنی ملت کے حق ہونے اور نبوی دعوت کے باطل ہونے پر—جس پر مومنین ایمان لائے تھے—یہ دلیل پیش کی کہ وہ دنیا میں مقام و مجلس کے لحاظ سے بہتر ہیں، تو وہ اس حقیقت کو بھول گئے کہ انسان کے لیے ایک دائمی اور ابدی زندگی ہے جس کی کوئی انتہا نہیں، اور اس کی اصل سعادت اسی زندگی کی سعادت میں ہے، جبکہ دنیا میں گزارے جانے والے چند دن اس لامتناہی زندگی کے مقابلے میں کوئی حیثیت نہیں رکھتے اور نہ ہی اسے اس سے بے نیاز کر سکتے ہیں۔\n\nعلاوہ ازیں، یہ دنیاوی لذتیں اس کے لیے سعادت کو یقینی نہیں بناتیں اور نہ ہی اسے اللہ کے غضب سے بچا سکتی ہیں اگر وہ کسی دن اس پر نازل ہو جائے، اور اللہ کا عذاب ظالموں سے دور نہیں ہے۔ پس وہ اللہ کی ناراضگی سے مامون نہیں ہیں، اور اس زندگی میں کوئی خیر نہیں جسے ہلاکت کی دھمکی لاحق ہو، اور نہ ہی اس نعمت میں کوئی بھلائی ہے جو ہر وقت زوال اور محرومی کی زد میں ہو۔\n\nاللہ نے اس کا جواب اپنے اس فرمان سے دیا: **وَكَمْ أَهْلَكْنا قَبْلَهُمْ** (اور ہم نے ان سے پہلے کتنی ہی نسلوں کو ہلاک کر دیا)۔ ظاہر یہ ہے کہ یہ جملہ حالیہ ہے اور **كَمْ** خبریہ ہے نہ کہ استفہامیہ۔ معنی یہ ہے کہ: وہ مومنین کو حقیر سمجھتے ہوئے یہ بودی شبہہ زبان پر لاتے ہیں کہ \"ہم تم سے مقام و مجلس میں بہتر ہیں\"، حالانکہ ہم نے ان سے پہلے بہت سی ایسی نسلیں ہلاک کر دیں جو ساز و سامان اور ظاہری مناظر کے اعتبار سے ان سے کہیں بہتر تھیں۔\n\nاللہ سبحانہ نے فرعون سے بھی اسی طرح کا شبہہ نقل کیا ہے اور اس کے بعد اس کے غرق ہونے اور ہلاکت کا تذکرہ فرمایا ہے، ارشاد ہوا: **وَنادى فِرْعَوْنُ فِي قَوْمِهِ قالَ يا قَوْمِ أَلَيْسَ لِي مُلْكُ مِصْرَ وَهذِهِ الْأَنْهارُ تَجْرِي مِنْ تَحْتِي أَفَلا تُبْصِرُونَ؟ أَمْ أَنَا خَيْرٌ مِنْ هذَا الَّذِي هُوَ مَهِينٌ وَلا يَكادُ يُبِينُ ، فَلَوْ لا أُلْقِيَ عَلَيْهِ أَسْوِرَةٌ مِنْ ذَهَبٍ** (اور فرعون نے اپنی قوم میں پکار کر کہا: اے میری قوم! کیا مصر کی بادشاہت میری نہیں ہے اور یہ نہریں میرے نیچے نہیں بہہ رہی ہیں؟ کیا تم دیکھتے نہیں ہو؟ یا میں اس شخص سے بہتر نہیں ہوں جو ذلیل ہے اور صاف بات بھی نہیں کر سکتا؟ تو پھر اس پر سونے کے کنگن کیوں نہیں اتارے گئے؟)—یہاں تک کہ فرمایا—**فَلَمَّا آسَفُونا انْتَقَمْنا مِنْهُمْ فَأَغْرَقْناهُمْ أَجْمَعِينَ فَجَعَلْناهُمْ سَلَفاً وَمَثَلاً لِلْآخِرِينَ** (پھر جب انہوں نے ہمیں غضبناک کیا تو ہم نے ان سے انتقام لیا اور ان سب کو غرق کر دیا، پھر ہم نے انہیں بعد والوں کے لیے پیش رو اور عبرت کا نمونہ بنا دیا)۔ (سورہ زخرف: ۵۱ تا ۵۶)\n\n**اللہ تعالیٰ کا فرمان:** **قُلْ مَنْ كانَ فِي الضَّلالَةِ فَلْيَمْدُدْ لَهُ الرَّحْمنُ مَدًّا**\n**قُلْ مَنْ كَانَ فِي الضَّلَالَةِ فَلْيَمْدُدْ لَهُ الرَّحْمَنُ مَدًّا حَتَّى إِذَا رَأَوْا مَا يُوعَدُونَ إِمَّا الْعَذَابَ وَإِمَّا السَّاعَةَ فَسَيَعْلَمُونَ مَنْ هُوَ شَرٌّ مَكَانًا وَأَضْعَفُ جُنْدًا**\n**آپ کہہ دیجیے کہ جو گمراہی میں ہے خدا اسے خوب ڈھیل دیتا ہے یہاں تک کہ جب وہ اس عذاب کو دیکھ لیں گے جس کا ان سے وعدہ کیا گیا ہے چاہے وہ دنیا کا عذاب ہو یا قیامت کی گھڑی، تو انہیں معلوم ہو جائے گا کہ کس کا ٹھکانا بدتر ہے اور کس کا لشکر زیادہ کمزور ہے۔** (سورہ مریم، آیت ۷۵)\n\nلفظ **كانَ** اللہ کے اس فرمان **مَنْ كانَ فِي الضَّلالَةِ** میں ان کے گمراہی پر اصرار اور استمرار پر دلالت کرتا ہے، نہ کہ محض کسی گمراہی کے وقوع پر۔ اسی وجہ سے انہیں امداد اور **استدراج** (استدراج — *اللہ کی طرف سے کسی گناہگار کو ڈھیل دینا یہاں تک کہ وہ اچانک پکڑ میں آ جائے*) کی سزا کی دھمکی مکمل ہوتی ہے، جو کہ گمراہی کے بعد مزید گمراہی ہے۔\n\nاور اللہ کا فرمان **فَلْيَمْدُدْ** امرِ غائب کا صیغہ ہے اور اس کا معنی یہ نکلتا ہے کہ رحمن پر واجب ہے کہ وہ اسے خوب ڈھیل دے، کیونکہ جب متکلم اپنے مخاطب کو حکم دے کہ وہ اسے کسی چیز کا حکم دے، تو اس کا مطلب یہ ہوتا ہے کہ متکلم نے اسے اپنے اوپر لازم کر لیا ہے۔\n\n**المد** اور **الأمداد** ایک ہی معنی میں ہیں، لیکن راغب نے \"المفردات\" میں ذکر کیا ہے کہ اکثر طور پر **الأمداد** پسندیدہ چیزوں میں استعمال ہوتا ہے اور **المد** ناپسندیدہ چیزوں میں۔ مراد یہ ہے کہ جس پر گمراہی مستحکم ہو گئی اور وہ اس پر اصرار کرتا رہا—اور یہاں کفار سے کنایہ ہے—تو اللہ نے اپنے اوپر لازم کر لیا ہے کہ وہ اسے ان چیزوں میں مزید ڈھیل دے جو اس کی گمراہی کا سبب ہیں، جیسے اس مقامِ کلام میں دنیاوی زیب و زینت، تاکہ وہ حق سے غافل رہے یہاں تک کہ اللہ کا حکم یعنی عذاب یا قیامت اچانک اور ہکا بکا کر دینے والی حالت میں آ پہنچے، تب اس پر حق ظاہر ہو جائے گا لیکن وہ اسے کوئی نفع نہ دے سکے گا۔\n\nپس اللہ کا فرمان: **حَتَّى إِذَا رَأَوْا مَا يُوعَدُونَ إِمَّا الْعَذَابَ وَإِمَّا السَّاعَةَ فَسَيَعْلَمُونَ** الخ، اس بات کی دلیل ہے کہ یہ ڈھیل (مد) درحقیقت اکرام کی صورت میں رسوائی (خذلان) ہے۔ اس سے مراد یہ ہے کہ انسان دنیاوی زندگی کی دھوکا دینے والی رونق میں مشغول ہو کر حق اور اس کی پیروی سے منحرف ہو جائے، پس اس پر حق صرف اسی وقت ظاہر ہو جب وہ اسے نفع نہ دے سکے، اور وہ وقت عذاب کے نزول یا قیامت کے برپا ہونے کا ہے۔\n\nجیسا کہ اللہ تعالیٰ نے فرمایا: **فَلَمْ يَكُ يَنْفَعُهُمْ إِيمانُهُمْ لَمَّا رَأَوْا بَأْسَنا سُنَّتَ اللهِ الَّتِي قَدْ خَلَتْ فِي عِبادِهِ** (پھر جب انہوں نے ہمارا عذاب دیکھ لیا تو ان کا ایمان لانا انہیں کچھ نفع نہ دے سکا، یہ اللہ کا وہ طریقہ ہے جو اس کے بندوں میں پہلے سے چلا آ رہا ہے)۔ (سورہ مومن: ۸۵)۔ اور فرمایا: **يَوْمَ يَأْتِي بَعْضُ آياتِ رَبِّكَ لا يَنْفَعُ نَفْساً إِيمانُها لَمْ تَكُنْ آمَنَتْ مِنْ قَبْلُ أَوْ كَسَبَتْ فِي إِيمانِها خَيْراً** (جس دن تیرے رب کی بعض نشانیاں آ جائیں گی، کسی ایسے شخص کو اس کا ایمان نفع نہ دے گا جو پہلے ایمان نہ لایا ہو یا اس نے اپنے ایمان میں کوئی نیکی نہ کمائی ہو)۔ (سورہ انعام: ۱۵۸)\n\nاللہ کے فرمان **رَأَوْا ما يُوعَدُونَ** میں جمع کی ضمیر کو **مَنْ** کی طرف پلٹانے میں اس کے معنی کی رعایت کی گئی ہے، جبکہ **فَلْيَمْدُدْ لَهُ** میں واحد کی ضمیر کو اس کی طرف پلٹانے میں اس کے لفظ کی رعایت کی گئی ہے۔\n\nاور اللہ کا فرمان: **فَسَيَعْلَمُونَ مَنْ هُوَ شَرٌّ مَكاناً وَأَضْعَفُ جُنْداً** (پس عنقریب وہ جان لیں گے کہ کون مکان کے لحاظ سے بدتر اور لشکر کے لحاظ سے زیادہ کمزور ہے) ان کے سابقہ قول **أَيُّ الْفَرِيقَيْنِ خَيْرٌ مَقاماً وَأَحْسَنُ نَدِيًّا** کے مقابلے میں لایا گیا ہے۔ رہا ان کا مکان جب وہ عذاب دیکھیں گے—اور ظاہر یہ ہے کہ اس سے مراد دنیا کا عذاب ہے—تو وہ وہی جگہ ہے جہاں اللہ کا عذاب ان پر نازل ہوگا، جیسا کہ قریش کے ان سرداروں کا ٹھکانا جن پر یہ آیات تلاوت کی گئی تھیں، عذاب کے نزول کے وقت بدر کا وہ کنواں (قلیبِ بدر) تھا جس میں ان کی لاشیں پھینک دی گئیں۔ اور رہا ان کا مکان جس دن وہ قیامت دیکھیں گے، تو وہ دائمی آگ ہے جو کہ ہلاکت کا گھر ہے۔ اور رہا ان کے لشکر کا ضعف، تو اس لیے کہ آج اللہ کے مقابلے میں ان کا کوئی بچانے والا نہیں ہے، اور جو کچھ انہوں نے اپنے لیے ساز و سامان اور افرادی قوت تیار کی تھی وہ سب بے کار ہو جائے گی اور اس کا کوئی اثر باقی نہ رہے گا۔\n\n**اللہ تعالیٰ کا فرمان:** **وَيَزِيدُ اللهُ الَّذِينَ اهْتَدَوْا هُدىً**\n**وَيَزِيدُ اللَّهُ الَّذِينَ اهْتَدَوْا هُدًى وَالْبَاقِيَاتُ الصَّالِحَاتُ خَيْرٌ عِنْدَ رَبِّكَ ثَوَابًا وَخَيْرٌ مَرَدًّا**\n**اور اللہ ہدایت پانے والوں کی ہدایت میں اضافہ کر دیتا ہے اور باقی رہ جانے والی نیکیاں تمہارے پروردگار کے نزدیک ثواب کے اعتبار سے بھی بہتر ہیں اور انجام کے اعتبار سے بھی بہتر ہیں۔** (سورہ مریم، آیت ۷۶)\n\n**الباقيات الصالحات :** وہ نیک اعمال جو اللہ کے ہاں محفوظ رہتے ہیں اور جن کا نتیجہ خوبصورت شکر اور عظیم اجر کی صورت میں نکلتا ہے، اور اللہ نے اپنے کلام میں کئی مقامات پر اس کا وعدہ فرمایا ہے۔\n\n**الثواب :** عمل کا بدلہ۔ راغب نے \"المفردات\" میں کہا ہے: **الثوب** کی اصل کسی چیز کا اپنی پہلی حالت کی طرف لوٹنا ہے جس پر وہ تھی، یا اس مقصود حالت کی طرف لوٹنا ہے جس کا ارادہ کیا گیا تھا—یہاں تک کہ کہا—اور ثواب وہ جزا ہے جو انسان کو اس کے اعمال کے بدلے میں ملتی ہے، اس جزا کو ثواب اس تصور سے کہا جاتا ہے کہ گویا یہ وہی عمل ہے جو لوٹ کر آیا ہے—یہاں تک کہ کہا—اور ثواب کا لفظ خیر اور شر دونوں میں استعمال ہوتا ہے لیکن عرفِ عام میں زیادہ تر خیر کے لیے مستعمل ہے۔ (اقتباس ختم)۔ اور **المرد** پلٹنے کی جگہ (اسمِ مکان) ہے اور اس سے مراد جنت ہے۔\n\nیہ آیت سابقہ آیت کے بیان کی تکمیل ہے، کیونکہ سابقہ آیت اہل ضلالت کے حال کو بیان کرتی ہے اور ذکر کرتی ہے کہ اللہ انہیں ڈھیل دے گا، پس وہ اپنی گمراہی میں بھٹکتے رہیں گے، حق سے منہ موڑے ہوئے، ایمان سے اعراض کیے ہوئے اور دنیاوی زندگی کی ان مصروفیات کے ساتھ کھیلتے ہوئے جو ان کے پاس ہیں، یہاں تک کہ عذاب یا قیامت انہیں اچانک آ لے گی اور ان پر حقیقتِ حال منکشف ہو جائے گی بغیر اس کے کہ وہ اس سے کوئی نفع اٹھا سکیں۔ یہ ان دو گروہوں میں سے ایک گروہ ہے جن کے بارے میں انہوں نے کہا تھا: **أَيُّ الْفَرِيقَيْنِ خَيْرٌ مَقاماً** الخ۔\n\nاور یہ آیت دوسرے گروہ یعنی مومنین کے حال کو بیان کرتی ہے کہ اللہ سبحانہ ہدایت یافتہ لوگوں یعنی مومنین کی ہدایت میں اضافہ فرماتا ہے، پس انہیں باقی رہنے والے نیک اعمال (باقیات صالحات) کی توفیق ملتی ہے جو اجر کے لحاظ سے بھی بہتر ہیں اور گھر کے لحاظ سے بھی، اور وہ گھر جنت اور اس کی دائمی نعمتیں ہیں۔ پس مومنین کے پاس زندگی کا جو سامان ہے یعنی دائمی نعمتیں، وہ کفار کے پاس موجود دھوکا دینے والی اور فانی زیب و زینت سے کہیں بہتر ہیں۔\n\nاللہ کے فرمان **عِنْدَ رَبِّكَ** (تمہارے رب کے نزدیک) میں اس طرف اشارہ ہے کہ مومنین کے ثواب اور ٹھکانے کے بہتر ہونے کا فیصلہ ایک الٰہی فیصلہ ہے جس میں قطعاً کوئی خطا یا غلطی نہیں ہو سکتی۔\n\nاور یہ دونوں آیات—جیسا کہ آپ دیکھ رہے ہیں—کفار کی اس دلیل یعنی ان کے قول **أَيُّ الْفَرِيقَيْنِ خَيْرٌ مَقاماً وَأَحْسَنُ نَدِيًّا** کا دوسرا جواب ہیں۔\n\n**اللہ تعالیٰ کا فرمان:** **أَفَرَأَيْتَ الَّذِي كَفَرَ بِآياتِنا وَقالَ لَأُوتَيَنَّ مالاً وَوَلَداً**\n**أَفَرَأَيْتَ الَّذِي كَفَرَ بِآيَاتِنَا وَقَالَ لَأُوتَيَنَّ مَالًا وَوَلَدًا**\n**کیا آپ نے اس شخص کو بھی دیکھا ہے جس نے ہماری نشانیوں کا انکار کیا اور یہ کہا کہ مجھے تو مال اور اولاد ضرور دی جائے گی۔** (سورہ مریم، آیت ۷۷)\n\nجس طرح سابقہ چار آیات کا سیاق یہ بتاتا ہے کہ مذکورہ فاسد دلیل بعض ان مشرکین کا قول تھی جن پر قرآن کی تلاوت کی گئی تو انہوں نے کلمہ حق کو زائل کرنے اور مومنین کو گمراہ و حقیر کرنے کے لیے یہ بات کہی، اسی طرح ان چار آیات کا سیاق بھی—جو کلمہ تعجب سے شروع ہوئی ہیں، سابقہ قول سے مشابہ قول پر مشتمل ہیں اور اس کے مناسب جواب پر ختم ہوئی ہیں—یہ بتاتا ہے کہ کچھ لوگ جو نبی اکرم صلی اللہ علیہ وآلہ وسلم پر ایمان لائے تھے یا ایمان لانے کے قریب تھے، کفار کی باتیں سن کر ان کی طرف مائل ہو گئے اور یہ کہتے ہوئے ان سے جا ملے کہ \"مجھے ضرور مال اور اولاد دی جائے گی\"، یعنی شرک کی ملت کی پیروی کر کے دنیا میں؛ گویا ان کے نزدیک اللہ پر ایمان لانے میں نحوست تھی اور بتوں کو معبود بنانے میں برکت۔ پس اللہ سبحانہ نے اپنے اس فرمان سے ان کی تردید کی: **أَطَّلَعَ الْغَيْبَ** (کیا اسے غیب کی خبر ہو گئی ہے) الخ۔\n\nرہی وہ بات جو اکثر مفسرین نے شانِ نزول کی روایات کی بنیاد پر ذکر کی ہے کہ یہ جملہ قریش کے ایک کٹر مشرک کا قول ہے جو اس نے خباب بن ارت سے اس وقت کہا تھا جب انہوں نے اس سے اپنے قرض کا مطالبہ کیا تھا، اور یہ کہ اس جملے \"مجھے ضرور مال اور اولاد دی جائے گی\" کا مطلب یہ ہے کہ جنت میں دی جائے گی تب میں اپنا قرض ادا کر دوں گا؛ تو یہ بات آیات کے سیاق سے میل نہیں کھاتی۔ کیونکہ یہ معلوم ہے کہ مشرکین سرے سے بعث (مرنے کے بعد اٹھنے) کے قائل ہی نہ تھے، لہٰذا اس کا یہ کہنا کہ \"جب میں دوبارہ اٹھایا جاؤں گا تو مجھے مال اور اولاد دی جائے گی اور تب میں اپنا قرض ادا کروں گا\" سوائے استہزاء اور تمسخر کے اور کچھ نہیں ہو سکتا، اور استہزاء کا جواب استدلال سے دینے کا کوئی معنی نہیں ہے جیسا کہ اللہ کے اس فرمان سے ظاہر ہے: **أَطَّلَعَ الْغَيْبَ أَمِ اتَّخَذَ عِنْدَ الرَّحْمنِ عَهْداً** (کیا اسے غیب کی خبر ہو گئی ہے یا اس نے رحمن سے کوئی عہد لے رکھا ہے) الخ۔\n\nاسی طرح کا ایک اور قول جو لغو ہے، ابو مسلم مفسر سے منقل ہے کہ یہ آیت ہر اس شخص کے بارے میں عام ہے جس میں یہ صفت پائی جائے۔\n\nپس اللہ کا فرمان: **أَفَرَأَيْتَ الَّذِي كَفَرَ بِآياتِنا** تعجب کے لیے لایا گیا ہے، اور لفظ **أَفَرَأَيْتَ** کلمہ تعجب ہے جسے \"فاء\" کے ذریعے سابقہ قول **أَيُّ الْفَرِيقَيْنِ خَيْرٌ مَقاماً وَأَحْسَنُ نَدِيًّا** پر متفرع کیا گیا ہے۔ کیونکہ اس کہنے والے کا کفر اور اس کا یہ قول کہ \"مجھے ضرور مال اور اولاد دی جائے گی\" ان کے کفر ہی کی ایک قسم ہے اور ان کے اس قول پر مبنی ہے جو انہوں نے مومنین سے کہا تھا کہ ان کے پاس کوئی خیر نہیں ہے، اور زندگی کی سعادت اور دنیا کی عزت و نعمت صرف کفار اور ان کی ملت ہی میں ہے۔\n\nیہیں سے یہ واضح ہوتا ہے کہ اس کے قول **وَقالَ لَأُوتَيَنَّ مالاً وَوَلَداً** کا اس کے قول **كَفَرَ بِآياتِنا** پر ایک طرح کا ترتب ہے، اور یہ کہ اس نے اللہ کی آیات کا کفر اس گمان میں کیا کہ یہ ایک مبارک اور بابرکت راستہ ہے جو اپنے چلنے والے کے لیے عزت و قدرت کھینچ لاتا ہے اور اسے دنیا میں خیر و سعادت عطا کرتا ہے، اور اس نے اس پر قسم بھی کھائی ہے جیسا کہ **لَأُوتَيَنَّ** میں \"لامِ قسم\" اور \"نونِ تاکید\" اس کی گواہی دے رہے ہیں۔\n\n**اللہ تعالیٰ کا فرمان:** **أَطَّلَعَ الْغَيْبَ أَمِ اتَّخَذَ عِنْدَ الرَّحْمنِ عَهْداً**\n**أَطَّلَعَ الْغَيْبَ أَمِ اتَّخَذَ عِنْدَ الرَّحْمَنِ عَهْدًا**\n**کیا اسے غیب کی خبر ہو گئی ہے یا اس نے رحمن سے کوئی عہد لے رکھا ہے۔** (سورہ مریم، آیت ۷۸)\n\nاللہ سبحانہ نے اس کے اس قول \"میں اپنے کفر کی وجہ سے ضرور مال اور اولاد دیا جاؤں گا\" کی تردید اس طرح فرمائی کہ یہ غیب پر تیر چلانے کے مترادف ہے جس کے علم کا اس کے پاس کوئی راستہ نہیں۔ وہ غیب پر مطلع نہیں ہے کہ اسے معلوم ہو جائے کہ اسے اس کے کفر کی وجہ سے وہ سب کچھ دیا جائے گا جس کی وہ امید لگائے بیٹھا ہے، اور نہ ہی اس نے اللہ سے کوئی عہد لے رکھا ہے کہ وہ اس پر مطمئن ہو جائے۔ یہاں نفی کو استفہامِ انکاری کی صورت میں پیش کیا گیا ہے۔\n\n**اللہ تعالیٰ کا فرمان:** **كَلَّا سَنَكْتُبُ ما يَقُولُ وَنَمُدُّ لَهُ مِنَ الْعَذابِ مَدًّا**\n**كَلَّا سَنَكْتُبُ مَا يَقُولُ وَنَمُدُّ لَهُ مِنَ الْعَذَابِ مَدًّا**\n**ہرگز نہیں، ہم اس کی بات کو لکھ لیں گے اور اس کے عذاب میں برابر اضافہ کرتے رہیں گے۔** (سورہ مریم، آیت ۷۹)\n\n**كَلَّا** رد و زجر (ڈانٹ ڈپٹ) کا کلمہ ہے اور آیت کا آخری حصہ اس بات کی دلیل ہے کہ اللہ سبحانہ اس کے ذریعے اس کہنے والے کے قول کے اس پہلو کی تردید فرما رہا ہے جس میں کفر پر مال و اولاد کے ملنے کا ترتب بیان کیا گیا تھا۔ اس کا خلاصہ یہ ہے کہ اس کے اس قول پر جو چیز مرتب ہوگی وہ مال و اولاد کا ملنا نہیں ہے—کیونکہ اس کے اسباب تو کچھ اور ہیں—بلکہ اس کے کفر اور غیب پر تیر چلانے کی وجہ سے عذاب کا طویل ہونا ہے۔ پس وہ اپنی اس بات کے ذریعے درحقیقت ایک ایسا طویل عذاب مانگ رہا ہے جو ایک کے بعد ایک آئے گا، کیونکہ یہی اس کے قول کا نتیجہ ہے نہ کہ مال و اولاد کا ملنا۔ اور ہم اس کے قول کو لکھ لیں گے اور اس پر اس کا وہ اثر مرتب کریں گے جو کہ عذاب کا طویل ہونا ہے؛ پس یہ آیت اللہ کے اس فرمان کی مانند ہے: **فَلْيَدْعُ نادِيَهُ سَنَدْعُ الزَّبانِيَةَ** (پس وہ اپنی مجلس کو بلا لے، ہم بھی عذاب کے فرشتوں کو بلا لیں گے)۔ (سورہ علق: ۱۸)\n\nیہیں سے یہ ظاہر ہوتا ہے کہ زیادہ قرینِ قیاس یہ ہے کہ اس کے قول کو لکھنے سے مراد اسے ثابت کرنا ہے تاکہ اس پر اس کا اثر مرتب ہو، نہ کہ اسے نامہ اعمال میں لکھنا تاکہ قیامت کے دن اس کا حساب لیا جائے جیسا کہ مفسرین نے اس کی تفسیر کی ہے۔ علاوہ ازیں، ان مفسرین کے قول کے مطابق اگلی آیت **وَنَرِثُهُ ما يَقُولُ** میں بغیر کسی ظاہر نکتے کے تکرار کا شائبہ پیدا ہوتا ہے۔\n\n**اللہ تعالیٰ کا فرمان:** **وَنَرِثُهُ ما يَقُولُ وَيَأْتِينا فَرْداً**\n**وَنَرِثُهُ مَا يَقُولُ وَيَأْتِينَا فَرْدًا**\n**اور جو کچھ وہ کہہ رہا ہے اس کے ہم وارث ہوں گے اور وہ ہمارے پاس اکیلا آئے گا۔** (سورہ مریم، آیت ۸۰)\n\nاس کے قول کا وارث ہونے سے مراد یہ ہے کہ وہ مر جائے گا اور فنا ہو جائے گا اور اپنا یہ قول \"مجھے میرے کفر کی وجہ سے مال اور اولاد دیا جائے گا\" پیچھے چھوڑ جائے گا۔ یہ قول اس کے لیے ایک ایسی خطا بن چکا تھا جو اس کے ساتھ اس طرح چمٹ گئی تھی جیسے انسان کے ساتھ اس کا مال چمٹا ہوتا ہے، اور وہ اللہ کے ہاں محفوظ ہے گویا وہ کوئی مال ہے جس کا وہ (اللہ) اس کے بعد وارث بنا ہے۔ اس کلام میں ایک لطیف استعارہ پایا جاتا ہے۔\n\nاور اللہ کا فرمان: **وَيَأْتِينا فَرْداً** یعنی وہ تنہا آئے گا اور اس کے ساتھ وہ کچھ نہ ہوگا جس کے ذریعے وہ مدد حاصل کرتا تھا یا اپنے وہم کے مطابق جس پر بھروسہ کرتا تھا۔ پس آیت کا خلاصہ یہ ہے کہ وہ ہمارے پاس اکیلا آئے گا اور اس کے پاس سوائے اس کے قول کے کچھ نہ ہوگا جسے ہم نے اس کے خلاف محفوظ کر رکھا ہے، پس ہم اس کے قول پر اس کا محاسبہ کریں گے اور اس کے لیے عذاب کو خوب دراز کر دیں گے۔\n\nیہ وہ معنی ہے جو اس بنیاد پر نکلتا ہے کہ آیات کے شروع میں اس کا قول **لَأُوتَيَنَّ مالاً وَوَلَداً** دنیا میں ملنے کی طرف ناظر ہو۔ لیکن اس بنیاد پر کہ یہ آخرت میں ملنے کی طرف ناظر ہو—جیسا کہ اکثر مفسرین نے اختیار کیا ہے—تو آیات کا معنی ویسا ہی ہوگا جیسا انہوں نے بیان کیا ہے: تعجب ہے اس شخص پر جس نے ہماری آیات کا کفر کیا اور وہ عاص بن وائل یا ولید بن مغیرہ ہے اور اس نے کہا: میں قسم کھاتا ہوں کہ جب میں دوبارہ اٹھایا جاؤں گا تو مجھے جنت میں مال اور اولاد دیا جائے گا۔ کیا اسے غیب کا علم ہو گیا ہے کہ اسے معلوم ہے کہ وہ جنت میں ہوگا؟—اور کہا گیا ہے: کیا اس نے لوحِ محفوظ میں دیکھ لیا ہے؟—یا اس نے رحمن سے \"لا الہ الا اللہ\" کہنے کے ذریعے کوئی عہد لے رکھا ہے جس کی وجہ سے وہ جنت میں داخل ہوگا؟—اور کہا گیا ہے: کیا اس نے کوئی نیک عمل آگے بھیجا ہے؟—ہرگز نہیں، معاملہ ویسا نہیں جیسا اس نے کہا۔ ہم اس کی بات کو لکھ لیں گے یعنی فرشتوں کو حکم دیں گے کہ اسے اس کے نامہ اعمال میں درج کر لیں اور اس کے لیے عذاب کو خوب دراز کر دیں گے، اور ہم اس کے قول کے وارث ہوں گے یعنی اس کے پاس جو مال اور اولاد ہے اسے ہلاک کر کے اور اس کی ملکیت کو باطل کر کے ہم اس کے وارث بن جائیں گے، اور وہ ہمارے پاس آئے گا یعنی آخرت میں اکیلا آئے گا، اس کے پاس مال، اولاد اور کوئی جتھہ یا ساز و سامان نہ ہوگا۔\n\n## (بحثِ روائی)\n\nتفسیر قمی میں ابوجارود کی روایت میں امام ابوجعفر علیہ السلام سے اللہ تعالیٰ کے اس فرمان: **أَفَرَأَيْتَ الَّذِي كَفَرَ بِآياتِنا ـ وَقالَ لَأُوتَيَنَّ مالاً وَوَلَداً** کے بارے میں مروی ہے کہ: \"یہ عاص بن وائل بن ہشام قرشی سہمی تھا، جو مذاق اڑانے والوں میں سے ایک تھا۔ خباب بن ارت کا عاص بن وائل پر کچھ حق (قرض) تھا، وہ اس کے پاس تقاضا کرنے آئے تو عاص نے ان سے کہا: کیا تم لوگ یہ دعویٰ نہیں کرتے کہ جنت میں سونا، چاندی اور ریشم ہوگا؟\nانہوں نے کہا: کیوں نہیں۔ اس نے کہا: تو پھر میرے اور تمہارے درمیان وعدے کی جگہ جنت ہے، خدا کی قسم! مجھے وہاں اس سے بہتر دیا جائے گا جو مجھے دنیا میں دیا گیا ہے۔\"\n\nاور \"الدر المنثور\" میں احمد، بخاری، مسلم، سعید بن منصور، عبد بن حمید، ترمذی، بیہقی (الدلائل میں)، ابن منذر، ابن ابی حاتم، ابن حبان اور ابن مردویہ نے خباب بن ارت سے روایت کی ہے، انہوں نے کہا: \"میں ایک لوہار تھا اور عاص بن وائل پر میرا قرض تھا۔ میں اس کے پاس تقاضا کرنے گیا تو اس نے کہا: خدا کی قسم! میں تیرا قرض ادا نہیں کروں گا جب تک تو محمد (صلی اللہ علیہ وآلہ وسلم) کا انکار نہ کر دے۔ میں نے کہا: خدا کی قسم! میں محمد کا انکار نہیں کروں گا یہاں تک کہ تو مر جائے اور پھر دوبارہ اٹھایا جائے۔ اس نے کہا: تو جب میں مر کر دوبارہ اٹھایا جاؤں گا تو میرے پاس مال اور اولاد ہوگی تب میں تجھے تیرا حق ادا کر دوں گا۔ اس پر اللہ نے یہ آیت نازل فرمائی: **أَفَرَأَيْتَ الَّذِي كَفَرَ بِآياتِنا** سے لے کر **وَيَأْتِينا فَرْداً** تک۔\"\n\nمیں کہتا ہوں: طبرانی نے بھی خباب سے اسی کے قریب روایت کی ہے۔ نیز سعید بن منصور نے حسن سے، انہوں نے رسول اللہ صلی اللہ علیہ وآلہ وسلم کے ایک صحابی سے روایت کی ہے جس میں خباب کا نام نہیں لیا گیا۔ اور ابن ابی حاتم اور ابن مردویہ نے ابن عباس سے، انہوں نے کئی صحابہ سے روایت کی ہے۔\n\nپہلے یہ بات گزر چکی ہے کہ یہ روایات آیات کے سیاق و سباق کے مطابق نہیں ہیں، کیونکہ روایات اس بات میں صریح ہیں کہ یہ جملہ عاص بن وائل کی زبان سے محض استہزاء اور تمسخر کے طور پر نکلا تھا، علاوہ ازیں قطعی تاریخی شواہد بھی اس کی تائید کرتے ہیں کہ مشرکین سرے سے بعث اور قیامت کے قائل ہی نہ تھے۔\n\nپھر یہ کہ آیات اس کے قول کی تردید استدلال (احتجاج) کے ذریعے کر رہی ہیں، اور اگر یہ کلمہ محض استہزاء ہوتا جس میں کوئی سنجیدگی نہ ہوتی تو اس پر استدلال کرنے کا کوئی معنی نہ تھا، کیونکہ استدلال صرف سنجیدہ قول پر ہی درست ہوتا ہے ورنہ وہ خود ہزل (مذاق) بن جاتا ہے۔ پس یہ روایات اپنے اس صریح بیان کے باوجود کہ یہ کلمہ استہزاء تھا، آیت پر منطبق نہیں ہوتیں۔\n\nاور اگر اسے کسی بعید تاویل کے طور پر اس رخ پر محمول کیا جائے کہ اس نے یہ بات خباب کو لاجواب کرنے اور شرمندہ کرنے کے لیے کہی تھی بغیر اس کے کہ وہ خود اس کا عقیدہ رکھتا ہو، اور یہ استہزاء کے طور پر نہ ہو! تب بھی مال کے ساتھ اولاد کے ذکر کی کوئی وجہ نہ تھی، اس کے لیے اتنا کہنا کافی تھا کہ \"مجھے مال دیا جائے گا\"۔ مزید یہ کہ ان میں سے بعض روایات میں ہے کہ اس نے خباب سے کہا: \"تم لوگ یہ گمان کرتے ہو کہ تم مال اور اولاد کی طرف لوٹو گے\"، حالانکہ صدرِ اسلام کے مسلمانوں میں یہ قول مشہور نہ تھا کہ جنت میں توالد و تناسل (بچے پیدا ہونا) ہوگا اور نہ ہی قرآن میں کہیں اس طرف اشارہ ملتا ہے۔ یہ پہلی بات۔\n\nدوسری بات یہ کہ اس کے قول **لَأُوتَيَنَّ** میں قسم اور اس قدر تاکید کی کوئی وجہ نہ تھی، کیونکہ کسی کو لاجواب کرنے کے لیے اتنی تاکید کی ضرورت نہیں ہوتی۔\n\nتیسری بات یہ کہ **لَأُوتَيَنَّ** میں \"ملنے\" کے لفظ کو بغیر کسی قید کے مطلق چھوڑ دینا اور اسے جنت یا آخرت کے ساتھ مقید نہ کرنا کسی ظاہر نکتے کے بغیر التباس (ابہام) پیدا کرتا ہے۔\n\nچوتھی بات یہ کہ اس کی تردید اور ابطال کے لیے صرف اللہ کا یہ فرمان کافی تھا: **كَلَّا سَنَكْتُبُ ما يَقُولُ وَنَمُدُّ لَهُ مِنَ الْعَذابِ** دونوں آیتوں کے آخر تک۔ رہا اللہ کا یہ فرمان: **أَطَّلَعَ الْغَيْبَ أَمِ اتَّخَذَ عِنْدَ الرَّحْمنِ عَهْداً** تو یہ اس پر قطعاً وارد نہیں ہوتا، کیونکہ کسی کو لاجواب کرنا اس بات پر موقوف نہیں ہوتا کہ جس چیز سے اسے لاجواب کیا جا رہا ہے اس کی سچائی کا علم ہو، بلکہ اکثر اوقات یہ جھوٹ کے علم کے ساتھ بھی جمع ہو جاتا ہے؛ اس کا دارومدار تو اس فریق کے التزام پر ہوتا ہے جسے لاجواب کرنا مقصود ہو یا ان چیزوں پر جو اس کے عقیدے کا لازمہ ہوں۔\n\nواضح رہے کہ اللہ کے فرمان **وَالْباقِياتُ الصَّالِحاتُ** کے ذیل میں نبی اکرم اور ائمہ اہل بیت علیہم افضل الصلاۃ سے بہت سی خبریں مروی ہیں جن کی طرف ہم نے کتاب کی تیرہویں جلد میں سورہ کہف کی آیت ۴۶ کے ذیل میں بحثِ روائی میں اشارہ کیا ہے۔"}