{"edition":"almizan_ur","name":"تفسیر المیزان","author":"Allamah Muhammad Husayn Tabatabai","language":"ur","text":"# آیات\n\n```arabic\nيَـٰٓأَيُّهَا ٱلَّذِينَ ءَامَنُوا۟ ٱتَّقُوا۟ ٱللَّهَ حَقَّ تُقَاتِهِۦ وَلَا تَمُوتُنَّ إِلَّا وَأَنتُم مُّسْلِمُونَ (١٠٢)\n```\n\n```urdu\nایمان والو اللہ سے اس طرح ڈرو جو ڈرنے کا حق ہے اور خبردار اس وقت تک نہ مرنا جب تک مسلمان نہ ہوجاؤ (۱۰۲)\n```\n\n```arabic\nوَٱعْتَصِمُوا۟ بِحَبْلِ ٱللَّهِ جَمِيعًا وَلَا تَفَرَّقُوا۟ ۚ وَٱذْكُرُوا۟ نِعْمَتَ ٱللَّهِ عَلَيْكُمْ إِذْ كُنتُمْ أَعْدَآءً فَأَلَّفَ بَيْنَ قُلُوبِكُمْ فَأَصْبَحْتُم بِنِعْمَتِهِۦٓ إِخْوَٰنًا وَكُنتُمْ عَلَىٰ شَفَا حُفْرَةٍ مِّنَ ٱلنَّارِ فَأَنقَذَكُم مِّنْهَا ۗ كَذَٰلِكَ يُبَيِّنُ ٱللَّهُ لَكُمْ ءَايَـٰتِهِۦ لَعَلَّكُمْ تَهْتَدُونَ (١٠٣)\n```\n\n```urdu\nاور اللہ کی ر سّی کو مضبوطی سے پکڑے رہو اور آپس میں تفرقہ نہ پیدا کرو اور اللہ کی نعمت کو یاد کرو کہ تم لوگ آپس میں دشمن تھے اس نے تمہارے دلوں میں اُلفت پیدا کردی تو تم اس کی نعمت سے بھائی بھائی بن گئے اور تم جہّنم کے کنارے پر تھے تو اس نے تمہیں نکال لیا اور اللہ اسی طرح اپنی آیتیں بیان کرتا ہے کہ شاید تم ہدایت یافتہ بن جاؤ (۱۰۳)\n```\n\n```arabic\nوَلْتَكُن مِّنكُمْ أُمَّةٌ يَدْعُونَ إِلَى ٱلْخَيْرِ وَيَأْمُرُونَ بِٱلْمَعْرُوفِ وَيَنْهَوْنَ عَنِ ٱلْمُنكَرِ ۚ وَأُو۟لَـٰٓئِكَ هُمُ ٱلْمُفْلِحُونَ (١٠٤)\n```\n\n```urdu\nاور تم میں سے ایک گروہ کو ایسا ہونا چاہئے جو خیر کی دعوت دے, نیکیوں کا حکم دے برائیوں سے منع کرے اور یہی لوگ نجات یافتہ ہیں (۱۰۴)\n```\n\n```arabic\nوَلَا تَكُونُوا۟ كَٱلَّذِينَ تَفَرَّقُوا۟ وَٱخْتَلَفُوا۟ مِنۢ بَعْدِ مَا جَآءَهُمُ ٱلْبَيِّنَـٰتُ ۚ وَأُو۟لَـٰٓئِكَ لَهُمْ عَذَابٌ عَظِيمٌ (١٠٥)\n```\n\n```urdu\nاور خبردار ان لوگوں کی طرح نہ ہوجاؤ جنہوں نے تفرقہ پیدا کیا اور واضح نشانیوں کے آجانے کے بعد بھی اختلاف کیا کہ ان کے لئے عذاب هعظیم ہے (۱۰۵)\n```\n\n```arabic\nيَوْمَ تَبْيَضُّ وُجُوهٌ وَتَسْوَدُّ وُجُوهٌ ۚ فَأَمَّا ٱلَّذِينَ ٱسْوَدَّتْ وُجُوهُهُمْ أَكَفَرْتُم بَعْدَ إِيمَـٰنِكُمْ فَذُوقُوا۟ ٱلْعَذَابَ بِمَا كُنتُمْ تَكْفُرُونَ (١٠٦)\n```\n\n```urdu\nقیامت کے دن جب بعض چہرے سفید ہوں گے اور بعض سیاہ. جن کے چہرے سیاہ ہوں گے ان سے کہا جائے گا کہ تم ایمان کے بعد کیوں کافر ہوگئے تھے اب اپنے کفر کی بنائ پر عذاب کا مزہ چکھو (۱۰۶)\n```\n\n```arabic\nوَأَمَّا ٱلَّذِينَ ٱبْيَضَّتْ وُجُوهُهُمْ فَفِى رَحْمَةِ ٱللَّهِ هُمْ فِيهَا خَـٰلِدُونَ (١٠٧)\n```\n\n```urdu\nاور جن کے چہرے سفید اور روشن ہوں گے وہ رحمت الٰہی میں ہمیشہ ہمیشہ رہیں گے (۱۰۷)\n```\n\n```arabic\nتِلْكَ ءَايَـٰتُ ٱللَّهِ نَتْلُوهَا عَلَيْكَ بِٱلْحَقِّ ۗ وَمَا ٱللَّهُ يُرِيدُ ظُلْمًا لِّلْعَـٰلَمِينَ (١٠٨)\n```\n\n```urdu\nیہ آیااُ الٰہی ہیں جن کی ہم حق کے ساتھ تلاوت کررہے ہیں اور اللہ عالمین کے بارے میں ہرگز ظلم نہیں چاہتا (۱۰۸)\n```\n\n```arabic\nوَلِلَّهِ مَا فِى ٱلسَّمَـٰوَٰتِ وَمَا فِى ٱلْأَرْضِ ۚ وَإِلَى ٱللَّهِ تُرْجَعُ ٱلْأُمُورُ (١٠٩)\n```\n\n```urdu\nزمین و آسمان میں جو کچھ ہے سب اللہ کے لئے ہے اور اسی کی طرف سارے امور کی باز گشت ہے (۱۰۹)\n```\n\n```arabic\nكُنتُمْ خَيْرَ أُمَّةٍ أُخْرِجَتْ لِلنَّاسِ تَأْمُرُونَ بِٱلْمَعْرُوفِ وَتَنْهَوْنَ عَنِ ٱلْمُنكَرِ وَتُؤْمِنُونَ بِٱللَّهِ ۗ وَلَوْ ءَامَنَ أَهْلُ ٱلْكِتَـٰبِ لَكَانَ خَيْرًا لَّهُم ۚ مِّنْهُمُ ٱلْمُؤْمِنُونَ وَأَكْثَرُهُمُ ٱلْفَـٰسِقُونَ (١١٠)\n```\n\n```urdu\nتم بہترین امت ہو جسے لوگوں کے لئے منظرعام پر لایا گیا ہے تم لوگوں کو نیکیوں کا حکم دیتے ہو اور برائیوں سے روکتے ہو اور اللہ پر ایمان رکھتے ہو اور اگر اہل کتاب بھی ایمان لے آتے تو ان کے حق میں بہتر ہوتا لیکن ان میں صرف چند مومنین ہیں اور اکثریت فاسق ہے (۱۱۰)\n```\n\n## (تفسیر و بیان)\n\nیہ آیات ان ارشادات کا تسلسل ہیں جن میں اہل ایمان کو مخاطب کر کے انہیں اہل کتاب (اہل الكتاب) کے شر اور ان کے پیدا کردہ فتنوں سے خبردار کیا گیا ہے، اور یہ بتایا گیا ہے کہ مومنین کے پاس وہ ذرائع موجود ہیں جن سے متمسک ہو کر وہ خود کو بچا سکتے ہیں تاکہ نہ گمراہ ہوں اور نہ ہی ہلاکت کے گڑھوں میں گریں۔ اس کے ساتھ ساتھ یہ کلام پچھلی باتوں کا ہی مابعد ہے اور سابقہ سیاق و سباق میں کوئی تبدیلی نہیں آئی، یعنی اہل کتاب کے حال کا تذکرہ ابھی ختم نہیں ہوا۔ اس پر دلیل اللہ تعالیٰ کا وہ فرمان ہے جو ان آیات کے بعد آ رہا ہے: **لَن يَضُرُّوكُمْ إِلَّا أَذًى** (وہ تمہیں معمولی اذیت کے سوا کوئی نقصان نہیں پہنچا سکیں گے)۔\n\n**اللہ تعالیٰ کا فرمان:**\n**يَا أَيُّهَا الَّذِينَ آمَنُوا اتَّقُوا اللَّهَ حَقَّ تُقَاتِهِ**\n**اے ایمان والو! اللہ سے ڈرو جیسا کہ اس سے ڈرنے کا حق ہے** [جوادی ترجمہ: سورہ آل عمران، آیت ۱۰۲]\n\nپہلے یہ بات گزر چکی ہے کہ تقویٰ (التقوى) — *حق اور صراطِ مستقیم کی طرف الٰہی رہنمائی کے نتیجے میں حاصل ہونے والی وہ کیفیت جو انسان کو گناہوں سے بچاتی ہے* — درحقیقت ایک قسم کا بچاؤ اور پرہیز ہے۔ جب یہ اللہ سبحانہ کا تقویٰ ہو تو اس کا مطلب اس کے عذاب سے بچنا اور پرہیز کرنا ہوتا ہے، جیسا کہ اللہ تعالیٰ نے فرمایا: **فَاتَّقُوا النَّارَ الَّتِي وَقُودُهَا النَّاسُ وَالْحِجَارَةُ** (پس اس آگ سے ڈرو جس کا ایندھن انسان اور پتھر ہیں)۔ یہ مقصد صرف اسی صورت میں حاصل ہو سکتا ہے جب انسان ان امور پر چلے جن کا اللہ ارادہ رکھتا ہے اور جن سے وہ راضی ہوتا ہے؛ یعنی اس کے اوامر کی تعمیل، اس کی نواہی سے اجتناب، اس کی نعمتوں پر شکر اور اس کی بلا و آزمائش پر صبر کرنا۔ یہ آخری دونوں باتیں (شکر اور صبر) درحقیقت شکر ہی کی طرف لوٹتی ہیں، اس معنی میں کہ ہر چیز کو اس کے اصل مقام پر رکھا جائے۔ خلاصہ یہ کہ اللہ سبحانہ کا تقویٰ یہ ہے کہ اس کی اطاعت کی جائے اور نافرمانی نہ ہو، اور جو کچھ وہ عطا کرے یا روک لے، اس میں اس کے سامنے سرِ تسلیم خم کر دیا جائے۔\n\nلیکن جب تقویٰ کو \"حقِ تقویٰ\" (حق التقوى) کے عنوان سے لیا جائے، جس میں اس کی اپنی جنس کا کوئی باطل یا فاسد عنصر شامل نہ ہو، تو یہ وہ خالص بندگی (العبودية) بن جاتی ہے جس میں انانیت (إنية) اور غفلت کی کوئی آمیزش نہیں ہوتی۔ یہ ایسی اطاعت ہے جس میں معصیت نہ ہو، ایسا شکر ہے جس میں کفر (ناشکری) نہ ہو، اور ایسا ذکر ہے جس میں نسیان (بھول چوک) نہ ہو۔ یہی اسلامِ حقیقی ہے، یعنی اسلام کے درجات میں سے بلند ترین درجہ۔ اس بنیاد پر اللہ تعالیٰ کے اس فرمان: **وَلَا تَمُوتُنَّ إِلَّا وَأَنْتُمْ مُسْلِمُونَ** کا معنی ہمارے اس قول کی طرح ہوگا کہ: \"تم اسی حالت (حقِ تقویٰ) پر ہمیشگی اختیار کرو یہاں تک کہ تمہیں موت آ جائے\"۔\n\nیہ معنی اس مفہوم سے مختلف ہے جو اللہ تعالیٰ کے اس فرمان سے حاصل ہوتا ہے: **فَاتَّقُوا اللَّهَ مَا اسْتَطَعْتُمْ** (پس اللہ سے ڈرو جتنا تم سے ہو سکے) [التغابن: ۱۶]۔ کیونکہ یہ آیت اس معنی میں ہے کہ جس چیز کی بھی تم استطاعت رکھتے ہو اس میں تقویٰ کو ترک نہ کرو، مگر یہ کہ استطاعت (الاستطاعة) — *کسی کام کو انجام دینے کی وہ قدرت جو افراد کی ہمت اور فہم کے مطابق مختلف ہوتی ہے* — اشخاص کی قوتوں، ان کے فہم اور ان کی ہمتوں کے اختلاف سے بدلتی رہتی ہے۔ اس میں کوئی شک نہیں کہ \"حقِ تقویٰ\" اس معنی میں جو ہم نے ذکر کیا، بہت سے لوگوں کی وسعت میں نہیں ہے؛ کیونکہ اس باطنی سفر میں ایسے مقامات، منزلیں اور خطرات ہیں جنہیں صرف عالمین (العالمون) ہی سمجھ سکتے ہیں، اور ایسی باریکیاں و لطافتیں ہیں جن سے صرف مخلصین (المخلصون) ہی آگاہ ہوتے ہیں۔ بسا اوقات تقویٰ کے مراحل میں سے کوئی مرحلہ ایسا ہوتا ہے جسے عام فہم اس قابل ہی نہیں سمجھتی کہ انسانی نفس اس کی استطاعت رکھ سکتا ہے، چنانچہ وہ اسے غیر مقدور ہونے کا قطعی فیصلہ دے دیتی ہے، حالانکہ حقیقی تقویٰ والے اسے پیچھے چھوڑ چکے ہوتے ہیں اور اپنی ہمتوں کے ساتھ اس سے بھی زیادہ کٹھن اور مشکل مراحل کی طرف متوجہ ہوتے ہیں۔\n\nپس اللہ کا فرمان: **فَاتَّقُوا اللَّهَ مَا اسْتَطَعْتُمْ** ایک ایسا کلام ہے جسے مختلف اذہان اپنے اپنے فہم کے مطابق مختلف معانی میں لیتے ہیں، جس طرح ہر شخص اپنی استطاعت پر اسے منطبق کرتا ہے۔ پھر یہی بات اس آیت یعنی **اتَّقُوا اللَّهَ حَقَّ تُقَاتِهِ وَلَا تَمُوتُنَّ إِلَّا وَأَنْتُمْ مُسْلِمُونَ** کو سمجھنے کا وسیلہ بنتی ہے کہ مراد یہ ہے کہ لوگ حقِ تقویٰ کی شاہراہ پر گامزن ہو جائیں اور اس مقام کے حصول اور اس میں ثابت قدمی کا قصد کریں۔ یہ بالکل صراطِ مستقیم (الصراط المستقيم) — *اللہ تک پہنچنے کا سیدھا اور بے خطا راستہ* — کی طرف ہدایت پانے کے مانند ہے جس پر مکمل طور پر چلنا صرف چیدہ اور یگانہ روزگار افراد (الأوحديون) کے لیے ہی ممکن ہوتا ہے، لیکن اس کے باوجود تمام لوگوں کو اس کی طرف دعوت دی جاتی ہے۔ پس ان دونوں آیات (اتقوا الله حق تقاته اور فاتقوا الله ما استطعتم) کا حاصل یہ نکلتا ہے کہ تمام لوگوں کو حقِ تقویٰ کی طرف بلایا جائے اور اس کی ترغیب دی جائے، پھر انہیں حکم دیا جائے کہ وہ اپنی قدرت اور استطاعت کے مطابق اس مقصد کی طرف سفر کریں؛ اس کا نتیجہ یہ ہوگا کہ سب لوگ تقویٰ کی راہ پر تو ہوں گے مگر اپنے فہم، ہمت اور اللہ کی طرف سے ملنے والی توفیق، تائید اور تسدید کے مطابق مختلف مراحل اور درجات پر فائز ہوں گے۔ ان دونوں آیات کے معنی میں تدبر سے یہی بات سامنے آتی ہے۔\n\nاسی سے یہ بھی ظاہر ہوتا ہے کہ دونوں آیات مضمون کے لحاظ سے ایک دوسرے کے خلاف نہیں ہیں، اور نہ ہی پہلی آیت (اتقوا الله حق تقاته) سے بعینہ وہی مراد ہے جو دوسری آیت (فاتقوا الله ما استطعتم) سے ہے، بلکہ پہلی آیت مقصد (المقصد) کی طرف دعوت دیتی ہے اور دوسری آیت اس راہ پر چلنے (السلوك) کی کیفیت بیان کرتی ہے۔\n\n**اللہ تعالیٰ کا فرمان:**\n**وَلَا تَمُوتُنَّ إِلَّا وَأَنْتُمْ مُسْلِمُونَ**\n**اور دیکھو مرنا نہیں مگر یہ کہ تم مسلمان رہو** [جوادی ترجمہ: سورہ آل عمران، آیت ۱۰۲]\n\nموت ان تکوینی امور میں سے ہے جو ہمارے اختیار کے دائرے سے باہر ہیں، اسی لیے اس سے اور اس جیسی دیگر چیزوں سے متعلق امر و نہی \"تکوینی\" ہوتے ہیں، جیسے اللہ کا فرمان: **فَقَالَ لَهُمُ اللَّهُ مُوتُوا** (پس اللہ نے ان سے فرمایا: مر جاؤ) اور اس کا فرمان: **أَن يَقُولَ لَهُ كُن فَيَكُونُ** (کہ وہ اسے کہتا ہے: ہو جا، تو وہ ہو جاتا ہے)۔ لیکن بسا اوقات ایک غیر اختیاری امر کو کسی اختیاری امر کے ساتھ اس طرح جوڑ دیا جاتا ہے کہ وہ دونوں مل کر ایک مرکب بن جاتے ہیں اور اس مرکب کی نسبت اختیار کی طرف ہو جاتی ہے، تب اس پر اعتباری امر و نہی لاگو ہو سکتے ہیں، جیسے اللہ تعالیٰ کا فرمان: **فَلَا تَكُونَنَّ مِنَ الْمُمْتَرِينَ** (پس تم شک کرنے والوں میں سے نہ ہونا)، اور **وَلَا تَكُن مَّعَ الْكَافِرِينَ** (اور کافروں کے ساتھ نہ ہونا)، اور **وَكُونُوا مَعَ الصَّادِقِينَ** (اور سچوں کے ساتھ ہو جاؤ) وغیرہ۔ یہاں وجود (الكون) کی اصل حقیقت تو انسان کے لیے ایک تکوینی لازمہ ہے جس میں اس کے اختیار کا کوئی دخل نہیں، لیکن جب اسے کسی اختیاری امر جیسے شک (الامتراء)، کفر یا سچائی کی پابندی کے ساتھ جوڑ دیا جاتا ہے، تو اسے ایک اختیاری امر شمار کیا جاتا ہے اور اس پر مولویانہ امر و نہی وارد ہوتے ہیں۔\n\nخلاصہ یہ کہ اسلام کے سوا کسی اور حالت میں مرنے سے جو نہی کی گئی ہے، وہ اسے اختیاری شمار کرنے کی وجہ سے ہے، اور انجام کار یہ اس بات سے کنایہ ہے کہ تمام حالات میں اسلام پر قائم رہنا لازم ہے تاکہ موت جب بھی آئے، انہی حالات میں سے کسی ایک میں واقع ہو، اور مرنے والا اسلام کی حالت میں مرے۔\n\n**اللہ تعالیٰ کا فرمان:**\n**وَاعْتَصِمُوا بِحَبْلِ اللَّهِ جَمِيعًا وَلَا تَفَرَّقُوا**\n**اور اللہ کی رسی کو سب مل کر مضبوطی سے پکڑ لو اور آپس میں تفرقہ نہ پیدا کرو** [جوادی ترجمہ: سورہ آل عمران، آیت ۱۰۳]\n\nاللہ سبحانہ نے اس سے پہلے کے ارشادات میں، یعنی **وَكَيْفَ تَكْفُرُونَ وَأَنْتُمْ تُتْلَىٰ عَلَيْكُمْ آيَاتُ اللَّهِ وَفِيكُمْ رَسُولُهُ ۗ وَمَن يَعْتَصِم بِاللَّهِ...** (اور تم کیسے کفر کرو گے جبکہ تمہارے سامنے اللہ کی آیات پڑھی جا رہی ہیں اور تمہارے درمیان اس کا رسول موجود ہے، اور جو اللہ سے متمسک ہو جائے...) میں یہ ذکر فرمایا کہ اللہ کی آیات اور اس کے رسول (کتاب و سنت) سے تمسک کرنا ہی درحقیقت اللہ سے متمسک ہونا (الاعتصام بالله) ہے، جس کے ساتھ متمسک ہونے والا محفوظ رہتا ہے اور اس کے لیے ہدایت کی ضمانت ہے۔ رسول کے دامن سے وابستگی دراصل کتاب کے دامن سے وابستگی ہے، کیونکہ کتاب ہی اس کا حکم دیتی ہے جیسے اس فرمان میں: **وَمَا آتَاكُمُ الرَّسُولُ فَخُذُوهُ وَمَا نَهَاكُمْ عَنْهُ فَانتَهُوا** (اور جو کچھ رسول تمہیں دیں اسے لے لو اور جس سے منع کریں اس سے رک جاؤ)۔\n\nاس آیت میں اس \"اعتصام\" کو جس کی ترغیب دی گئی تھی، \"حبل اللہ\" (اللہ کی رسی) سے اعتصام میں بدل دیا گیا، جس کا نتیجہ یہ نکلا کہ حبل اللہ سے مراد وہ کتاب ہے جو اللہ کی طرف سے نازل ہوئی، اور وہی ہے جو بندے اور رب کے درمیان رابطہ قائم کرتی ہے اور آسمان کو زمین سے جوڑتی ہے۔ اگر آپ چاہیں تو یوں کہہ لیں کہ حبل اللہ سے مراد قرآن اور نبی ﷺ ہیں، کیونکہ آپ جان چکے ہیں کہ ان سب کا انجام ایک ہی ہے۔\n\nقرآن اگرچہ صرف حقِ تقویٰ اور ثابت قدم اسلام ہی کی دعوت دیتا ہے، لیکن اس آیت کا مقصد پچھلی آیت (جو حقِ تقویٰ اور اسلام پر موت کا حکم دیتی ہے) کے مقصد سے مختلف ہے۔ پچھلی آیت فرد کے حکم سے متعلق ہے، جبکہ یہ آیت ایک مجتمع گروہ اور جماعت کے حکم سے متعلق ہے، جس کی دلیل لفظ \"جمیعاً\" (سب مل کر) اور \"ولا تفرقوا\" (تفرقہ نہ کرو) ہے۔ پس یہ آیات اسلامی معاشرے کو کتاب و سنت سے متمسک ہونے کا ویسا ہی حکم دیتی ہیں جیسا کہ فرد کو دیتی ہیں۔\n\n**اللہ تعالیٰ کا فرمان:**\n**وَاذْكُرُوا نِعْمَتَ اللَّهِ عَلَيْكُمْ إِذْ كُنتُمْ أَعْدَاءً فَأَلَّفَ بَيْنَ قُلُوبِكُمْ فَأَصْبَحْتُم بِنِعْمَتِهِ إِخْوَانًا**\n**اور اللہ کی اس نعمت کو یاد کرو کہ تم آپس میں دشمن تھے اس نے تمہارے دلوں میں الفت پیدا کر دی تو تم اس کی نعمت سے بھائی بھائی بن گئے** [جوادی ترجمہ: سورہ آل عمران، آیت ۱۰۳]\n\nجملہ \"إذ كنتم\" (جب تم تھے) اس نعمت کا بیان ہے جس کا ذکر ہوا، اور اسی پر اس قول کا عطف ہے: **وَكُنتُمْ عَلَىٰ شَفَا حُفْرَةٍ مِّنَ النَّارِ فَأَنقَذَكُم مِّنْهَا** (اور تم آگ کے گڑھے کے کنارے پر تھے تو اس نے تمہیں اس سے بچا لیا)۔\n\nاس نعمت کو یاد کرنے کا حکم قرآن کے اس اسلوب پر مبنی ہے کہ وہ اپنی تعلیمات کی بنیاد علل اور اسباب کے بیان پر رکھتا ہے، اور خیر و ہدایت کی طرف اس کے اپنے راستے سے بلاتا ہے، نہ کہ اندھی تقلید (التقليد العامي المعمى) کا حکم دے کر۔ الٰہی تعلیمات سے یہ بات بعید ہے کہ وہ لوگوں کو سعادت — *جو کہ نافع علم اور صالح عمل کا نام ہے* — کی طرف ہدایت دے اور پھر انہیں تقلید کے صحرا اور جہالت کی تاریکی میں گرنے کا حکم دے۔\n\nلیکن یہاں یہ بات مشتبہ نہیں ہونی چاہیے اور نہ ہی تدبر کرنے والے محقق کے لیے حالات خلط ملط ہونے چاہئیں؛ اللہ سبحانہ لوگوں کو ان کی حقیقی سعادت کی تعلیم دیتا ہے اور اس کی وجہ بھی بتاتا ہے تاکہ وہ حقائق کے ایک دوسرے کے ساتھ ربط کو بصیرت کے ساتھ دیکھ سکیں، اور یہ جان لیں کہ یہ سب توحید (التوحيد) — *اللہ تعالیٰ کی ذات، صفات اور افعال میں مطلق وحدانیت* — کے منبع سے فیض یاب ہو رہے ہیں۔ اس کے ساتھ ساتھ ان پر اللہ کے لیے سرِ تسلیم خم کرنا واجب ہے کیونکہ وہ اللہ رب العالمین ہے، اور اس کی رسی سے متمسک ہونا واجب ہے کیونکہ وہ اللہ رب العالمین کی رسی ہے، جیسا کہ ان آیات کے آخر میں اس قول سے اشارہ ملتا ہے: **تِلْكَ آيَاتُ اللَّهِ نَتْلُوهَا عَلَيْكَ...** (یہ اللہ کی آیات ہیں جو ہم آپ کو پڑھ کر سناتے ہیں)۔\n\nخلاصہ یہ کہ اللہ نے انہیں حکم دیا کہ وہ کسی بات کو قبول نہ کریں اور کسی حکم کی اطاعت نہ کریں مگر اس کی وجہ کے علم کے ساتھ؛ پھر اس نے اپنی ذات کے لیے مطلق تسلیم کا حکم دیا اور اس کی وجہ یہ بتائی کہ وہی اللہ ہے جو ان کا علی الاطلاق مالک ہے، پس ان کے لیے وہی ہے جو وہ ان کے بارے میں چاہے اور ان میں تصرف کرے۔ پھر اس نے اپنے رسول کی لائی ہوئی باتوں کی مطلق اطاعت کا حکم دیا اور اس کی وجہ یہ بتائی کہ وہ رسول ہے جس کا کام صرف پیغام پہنچانا (البلاغ) ہے۔ پھر وہ ان سے حقائقِ معارف اور سعادت کے راستوں کے بارے میں کلام کرتا ہے اور ان سب میں ایک عمومی وجہ بیان کرتا ہے تاکہ وہ معارف کے روابط اور سعادت کے راستوں کی طرف ہدایت پائیں اور اصلِ توحید کو پا لیں۔ نیز وہ اس الٰہی ادب سے آراستہ ہوں تاکہ صحیح فکر کے راستے پر قدرت حاصل کریں اور حق بات کہنے کا طریقہ جان لیں، یوں وہ علم کے ساتھ زندہ ہوں اور تقلید سے آزاد رہیں۔ اس کا نتیجہ یہ نکلے گا کہ اگر وہ ثابت شدہ دینی معارف یا ان سے ملحقہ امور میں کسی حکم کی وجہ جان لیں گے تو اسے اختیار کر لیں گے، اور اگر نہ جان سکیں گے تو رد کرنے سے رک جائیں گے اور اس کے ثابت ہونے کے بعد بغیر کسی رد یا اعتراض کے بحث و تدبر کے ذریعے اس کے حصول کی طرف رجوع کریں گے۔\n\nیہ بات اس سے بالکل مختلف ہے کہ یہ کہا جائے: \"دین کی بنیاد اس پر ہے کہ اللہ اور رسول سے بھی کوئی چیز اس وقت تک قبول نہ کی جائے جب تک دلیل نہ مل جائے\"؛ کیونکہ یہ انتہائی احمقانہ رائے اور بدترین قول ہے، جس کا حاصل یہ نکلتا ہے کہ اللہ اپنے بندوں سے یہ چاہتا ہے کہ وہ دلیل کے موجود ہونے کے بعد دلیل کا مطالبہ کریں! حالانکہ اس کی ربوبیت اور ملکیت ہی تسلیم کے وجوب اور حکم کے نفاذ پر ہر دلیل کی اصل ہے۔ اور اس کے رسول کی رسالت ہی اس بات کی دلیل ہے کہ وہ جو کچھ اللہ کی طرف سے ادا کر رہے ہیں (وہ حق ہے)، پس اس نکتے کو سمجھیں۔ یا پھر اس کا حاصل یہ نکلتا ہے کہ ان امور میں اس کی ربوبیت کو لغو قرار دے دیا جائے جن میں وہ اپنی ربوبیت کے ساتھ تصرف فرماتا ہے، اور یہ تضاد کے سوا کچھ نہیں۔ حاصلِ کلام یہ کہ اسلامی مسلک اور نبوی طریقہ صرف علم کی طرف دعوت ہے نہ کہ تقلید کی طرف، جیسا کہ وہ مقلدین گمان کرتے ہیں جو خود کو نقاد کہلواتے ہیں۔\n\nاس بات کے ذکر کی وجہ کہ یہ ایک نعمت ہے (**نعمة الله عليكم**)، شاید اس نکتے کی طرف اشارہ ہے جس کا ہم نے ذکر کیا، یعنی جس اتحاد اور اجتماع کی ہم نے تمہیں دعوت دی ہے اس کی دلیل وہ ہے جس کا تم نے مشاہدہ کیا ہے؛ یعنی دشمنی کی کڑواہٹ اور محبت، الفت و بھائی چارے کی مٹھاس، اور آگ کے گڑھے کے کنارے پہنچ جانا اور پھر اس سے نجات پانا۔ ہم تمہیں یہ دلیل اس لیے یاد دلا رہے ہیں کہ تم یہ جان لو کہ یہ ہماری طرف سے تم پر ایک نعمت ہے، تاکہ تم پہچان لو کہ اس اجتماع میں، ان تمام چیزوں کی طرح جن کی ہم تمہیں دعوت دیتے ہیں، تمہاری سعادت، راحت اور کامیابی ہے۔\n\nاللہ تعالیٰ نے جو دو دلیلیں ذکر فرمائیں، ان میں سے ایک یعنی **إذ كنتم أعداء** (جب تم دشمن تھے) تجربے کی اصل پر مبنی ہے، اور دوسری یعنی **وكنتم على شفا حفرة** (اور تم گڑھے کے کنارے پر تھے) عقلی بیان کے طریقے پر ہے جیسا کہ ظاہر ہے۔\n\nفرمانِ الٰہی **فأصبحتم بنعمته إخواناً** (پس تم اس کی نعمت سے بھائی بھائی بن گئے) میں اس احسان کا تکرار ہے جس پر **واذكروا نعمة الله عليكم** دلالت کرتا ہے۔ یہاں نعمت سے مراد تالیفِ قلب (دلوں کا جوڑنا) ہے، اور اس بھائی چارے (الاخوّة) سے مراد جو اس نعمت کے ذریعے پیدا اور محقق ہوتا ہے، وہ بھی دلوں کی الفت ہی ہے، پس یہاں بھائی چارہ ایک ادعائی حقیقت ہے۔\n\nیہ بھی ممکن ہے کہ یہ اس بات کی طرف اشارہ ہو جو اللہ کے اس فرمان میں شامل ہے: **إِنَّمَا الْمُؤْمِنُونَ إِخْوَةٌ** (مومنین تو بس بھائی بھائی ہیں) [الحجرات: ۱۰]، یعنی ان کے درمیان بھائی چارے کی تشریع (قانون سازی)۔ کیونکہ مومنین کے درمیان ایک شرعی بھائی چارہ ہے جس سے اہم حقوق وابستہ ہیں۔\n\n**اللہ تعالیٰ کا فرمان:**\n**وَكُنتُمْ عَلَىٰ شَفَا حُفْرَةٍ مِّنَ النَّارِ فَأَنقَذَكُم مِّنْهَا**\n**اور تم آگ کے گڑھے کے کنارے پر تھے تو اس نے تمہیں اس سے بچا لیا** [جوادی ترجمہ: سورہ آل عمران، آیت ۱۰۳]\n\n\"شفا الحفرة\" گڑھے کے اس کنارے کو کہتے ہیں جہاں کھڑا ہونے والا اس میں گرنے کے قریب ہو۔\n\nاگر یہاں آگ (النار) سے مراد آخرت کی آگ ہے، تو ان کے گڑھے کے کنارے پر ہونے کا مطلب یہ ہے کہ وہ کافر تھے اور ان کے اور آگ میں گرنے کے درمیان صرف موت کا فاصلہ تھا، جو انسان سے آنکھ کی سیاہی کے اس کی سفیدی سے قریب ہونے سے بھی زیادہ قریب ہے، پس اللہ نے انہیں ایمان کے ذریعے اس سے بچا لیا۔\n\nاور اگر اس سے مراد ان کے اس فاسد معاشرے کا حال بیان کرنا ہے جس میں وہ اپنے ایمان اور تالیفِ قلب سے پہلے زندگی گزار رہے تھے، اور آگ سے مراد جنگیں اور منازعات ہوں — جو کہ استعارے کے طور پر ایک عام استعمال ہے — تو مقصد یہ ہے کہ وہ معاشرہ جس کی بنیاد دلوں کی پراگندگی اور مقاصد و خواہشات کے اختلاف پر ہو، وہ لازمی طور پر کسی ایک ایسی دلیل پر نہیں چل سکتا جو انہیں ایک ہی منزل کی طرف لے جائے، بلکہ وہ ایسی مختلف دلیلوں پر چلتا ہے جو ذاتی میلانات اور لغو انفرادی تحکمات کے مطابق بدلتی رہتی ہیں۔ ایسی صورتحال انہیں شدید ترین اختلاف کی طرف لے جاتی ہے، بدترین تنازع کے قریب کر دیتی ہے، ہمیشہ لڑائی بھڑائی کی دھمکی دیتی ہے اور فنا و زوال کا پیغام سناتی ہے۔ یہی وہ آگ ہے جو نہ باقی چھوڑتی ہے اور نہ معاف کرتی ہے، اور یہ جہالت کے اس گڑھے پر لگی ہوتی ہے جس میں گرنے والے کے لیے نہ کوئی جائے پناہ ہے اور نہ خلاصی۔\n\nپس یہ لوگ جو مسلمانوں کا ایک گروہ تھے اور اپنے کفر کے بعد اس آیت کے نزول سے پہلے ایمان لا چکے تھے، اور جو ان آیات کے اولین مخاطب ہیں، وہ اسلام سے پہلے اپنی زندگی کا عرصہ ہر لمحہ جنگوں اور لڑائیوں کے خطرے میں ہی گزارتے تھے۔ نہ امن تھا، نہ راحت اور نہ فراغت۔ وہ یہ نہیں جانتے تھے کہ اس عمومی امن کی حقیقت کیا ہے جو معاشرے کے تمام پہلوؤں یعنی جاہ و مال، عزت و جان وغیرہ کو محیط ہوتا ہے۔\n\nپھر جب وہ حبل اللہ سے متمسک ہونے پر جمع ہو گئے، اور ان کے لیے سعادت کی نشانیاں ظاہر ہوئیں، اور انہوں نے نعمتوں کی مٹھاس کا کچھ ذائقہ چکھ لیا، تو انہوں نے اس بات کی سچائی کو پا لیا جس کی اللہ انہیں یاد دہانی کرا رہا ہے، یعنی خوشگوار نعمت اور لذیذ سعادت۔ چنانچہ یہ خطاب ان کے اور دوسروں کے نفوس پر زیادہ اثر انداز ہوا۔\n\nاسی لیے کلام کی بنیاد اور دعوت کی اساس محض تقدیر اور فرض پر نہیں بلکہ مشاہدے اور وجدان پر رکھی گئی ہے، کیونکہ دیکھنا سننے جیسا نہیں ہوتا اور تجربات محض مفروضوں کے برابر نہیں ہوتے۔ اسی وجہ سے آنے والی تنبیہ میں، یعنی **وَلَا تَكُونُوا كَالَّذِينَ تَفَرَّقُوا وَاخْتَلَفُوا...** (اور ان لوگوں کی طرح نہ ہو جانا جو تفرقے میں پڑ گئے اور اختلاف کیا...) میں ان سے پہلے والوں کے حال کی طرف اشارہ کیا گیا ہے، کیونکہ ان کا انجام مومنین کی آنکھوں اور کانوں کے سامنے تھا، پس انہیں چاہیے کہ ان سے اور ان کے انجام سے عبرت حاصل کریں، نہ ان کے نقشِ قدم پر چلیں اور نہ ان کا راستہ اختیار کریں۔\n\nپھر اللہ نے انہیں اس بیان کی خصوصیت پر متنبہ کرتے ہوئے فرمایا: **كَذَٰلِكَ يُبَيِّنُ اللَّهُ لَكُمْ آيَاتِهِ لَعَلَّكُمْ تَهْتَدُونَ** (اسی طرح اللہ تمہارے لیے اپنی آیات بیان کرتا ہے تاکہ تم ہدایت پا جاؤ)۔\n\n**اللہ تعالیٰ کا فرمان:**\n**وَلْتَكُن مِّنكُمْ أُمَّةٌ يَدْعُونَ إِلَى الْخَيْرِ وَيَأْمُرُونَ بِالْمَعْرُوفِ وَيَنْهَوْنَ عَنِ الْمُنكَرِ...**\n**اور تم میں سے ایک گروہ ایسا ہونا چاہیے جو خیر کی طرف دعوت دے اور نیکیوں کا حکم دے اور برائیوں سے روکے** [جوادی ترجمہ: سورہ آل عمران، آیت ۱۰۴]\n\nقطعی تجربہ اس بات پر دلالت کرتا ہے کہ وہ معلومات جو انسان اپنی زندگی میں اپنے لیے فراہم کرتا ہے — اور انسان اپنے لیے وہی کچھ جمع کرتا ہے جس سے اسے نفع پہنچے — وہ جس طریقے سے بھی حاصل کی گئی ہوں اور جس صورت میں بھی ذخیرہ کی گئی ہوں، وہ اس سے زائل ہو جاتی ہیں اگر وہ انہیں یاد نہ رکھے اور عمل کے ذریعے ان کی تکرار پر ہمیشگی اختیار نہ کرے۔ ہمیں اس میں کوئی شک نہیں کہ عمل اپنے تمام پہلوؤں میں علم کے گرد گھومتا ہے؛ علم کی قوت سے قوی ہوتا ہے، اس کے ضعف سے ضعیف ہوتا ہے، اس کی اصلاح سے درست ہوتا ہے اور اس کے بگاڑ سے فاسد ہو جاتا ہے۔ اللہ سبحانہ نے ان دونوں کے حال کی مثال اس فرمان میں دی ہے: **وَالْبَلَدُ الطَّيِّبُ يَخْرُجُ نَبَاتُهُ بِإِذْنِ رَبِّهِ ۖ وَالَّذِي خَبُثَ لَا يَخْرُجُ إِلَّا نَكِدًا** (اور پاکیزہ زمین کا سبزہ اس کے رب کے حکم سے نکلتا ہے اور جو زمین گندی ہے اس کا سبزہ ناقص ہی نکلتا ہے) [الاعراف: ۵۸]۔\n\nاور ہمیں اس میں بھی شک نہیں کہ علم اور عمل تاثیر میں ایک دوسرے کے عکس ہیں؛ علم عمل کی طرف سب سے بڑا داعی ہے، اور واقع ہونے والا مشہود عمل انسان کو سکھانے والا سب سے بڑا معلم ہے۔\n\nیہی وہ نکتہ ہے جو اس صالح معاشرے کو، جس کے پاس نافع علم اور صالح عمل موجود ہے، اس بات کی دعوت دیتا ہے کہ وہ اپنی معرفت اور ثقافت کی حفاظت کریں، اور جو ان کے نزدیک معروف خیر کے راستے سے پیچھے رہ جائے اسے اس کی طرف واپس لائیں، اور جو معروف خیر کے راستے سے بھٹک کر ان کے نزدیک منکر شر کی وادی میں جا گرے اسے شر کی ہلاکت میں پڑنے سے روکیں اور اسے منع کریں۔\n\nیہی وہ تعلیم کے ذریعے دعوت، امر بالمعروف اور نہی عن المنکر ہے جسے اللہ اس آیت میں ان الفاظ کے ساتھ ذکر فرماتا ہے: **يَدْعُونَ إِلَى الْخَيْرِ وَيَأْمُرُونَ بِالْمَعْرُوفِ وَيَنْهَوْنَ عَنِ الْمُنكَرِ**۔\n\nیہیں سے خیر اور شر کے لیے \"معروف\" اور \"منکر\" کی تعبیر استعمال کرنے کا راز ظاہر ہوتا ہے، کیونکہ کلام کی بنیاد پچھلی آیت کے اس قول پر ہے: **وَاعْتَصِمُوا بِحَبْلِ اللَّهِ جَمِيعًا وَلَا تَفَرَّقُوا**۔ یہ معلوم ہے کہ جس معاشرے کی یہ شان ہو، اس میں \"معروف\" (جانی پہچانی بات) وہی ہوگی جو خیر ہے، اور \"منکر\" (ناپسندیدہ و اجنبی بات) وہی ہوگی جو شر ہے۔ اگر اس نکتے کا اعتبار نہ کیا جائے تو خیر و شر کو معروف و منکر کہنے کی وجہ یہ ہوگی کہ خیر و شر دین کی نظر میں معروف و منکر ہیں، نہ کہ خارجی عمل کے اعتبار سے۔\n\nرہی بات اللہ کے اس قول کی: **وَلْتَكُن مِّنكُمْ أُمَّةٌ**، تو کہا گیا ہے کہ یہاں \"مِن\" تبعیض (کچھ حصہ بتانے) کے لیے ہے، اس بنیاد پر کہ امر بالمعروف، نہی عن المنکر اور اسی طرح دعوت، واجباتِ کفائیہ میں سے ہیں۔\n\nاور بسا اوقات یہ بھی کہا گیا ہے کہ \"مِن\" بیانیہ ہے اور اس سے مراد یہ ہے کہ \"تم اس صالح اجتماع کے ساتھ ایک ایسی امت بن جاؤ جو خیر کی طرف دعوت دے\"۔ اس صورت میں کلام اس طرح ہوگا جیسے ہم کہیں: \"تمہاری طرف سے میرا ایک دوست ہونا چاہیے\" یعنی \"تم میرے دوست بن جاؤ\"۔ ظاہر یہ ہے کہ \"مِن\" کے بیانیہ ہونے سے مراد اس کا نشوئی اور ابتدائی ہونا ہے۔\n\nدرست بات یہ کہنی چاہیے کہ \"مِن\" کے تبعیضی یا بیانیہ ہونے کی بحث سے کوئی حاصل نتیجہ برآمد نہیں ہوتا، کیونکہ دعوت، امر بالمعروف اور نہی عن المنکر ایسے امور ہیں کہ اگر یہ واجب ہوں تو اپنی طبیعت کے اعتبار سے واجباتِ کفائیہ ہی ہوں گے؛ کیونکہ مقصد حاصل ہو جانے کے بعد دعوت، امر اور نہی کا کوئی معنی نہیں رہتا۔ پس اگر یہ فرض کر لیا جائے کہ پوری امت ہی خیر کی طرف بلانے والی، نیکی کا حکم دینے والی اور برائی سے روکنے والی ہے، تو اس کا مطلب یہ ہوگا کہ ان میں وہ لوگ موجود ہیں جو ان وظائف کو انجام دے رہے ہیں۔ پس امر بہرصورت بعض پر ہی قائم ہے؛ خطاب اگر بعض کے لیے ہے تو واضح ہے، اور اگر سب کے لیے ہے تو وہ بھی بعض کے اعتبار سے ہی ہے۔ دوسرے لفظوں میں: ذمہ دار سب ہیں اور ثواب پانے والے وہ بعض ہیں (جو اسے انجام دیں)۔ اسی لیے اللہ نے اس کے بعد فرمایا: **وَأُولَٰئِكَ هُمُ الْمُفْلِحُونَ** (اور وہی لوگ فلاح پانے والے ہیں)۔ پس ظاہر یہی ہے کہ \"مِن\" تبعیضی ہے، اور اہل زبان کے کلام میں اس طرح کی ترکیب سے یہی ظاہر ہوتا ہے اور کسی دلیل کے بغیر اس سے انحراف نہیں کیا جاتا۔\n\nواضح رہے کہ یہ تینوں موضوعات یعنی دعوت، امر بالمعروف اور نہی عن المنکر طویل اور گہری تفسیری ابحاث کے حامل ہیں جنہیں ہم انشاء اللہ کسی مناسب مقام پر پیش کریں گے۔ اسی طرح ان سے متعلق علمی، نفسیاتی اور سماجی ابحاث بھی وہیں ذکر ہوں گی۔\n\n**اللہ تعالیٰ کا فرمان:**\n**وَلَا تَكُونُوا كَالَّذِينَ تَفَرَّقُوا وَاخْتَلَفُوا مِن بَعْدِ مَا جَاءَهُمُ الْبَيِّنَاتُ...**\n**اور ان لوگوں کی طرح نہ ہو جانا جو تفرقے میں پڑ گئے اور واضح نشانیاں آنے کے بعد بھی اختلاف کیا** [جوادی ترجمہ: سورہ آل عمران، آیت ۱۰۵]\n\nیہ بعید نہیں کہ اللہ کا قول **مِن بَعْدِ مَا جَاءَهُمُ الْبَيِّنَاتُ** صرف **وَاخْتَلَفُوا** سے متعلق ہو، اور اس صورت میں \"تفرق\" سے مراد ابدان کا بکھرنا اور تشتت ہوگا، جبکہ \"اختلاف\" سے مراد عقیدے کا اختلاف ہوگا۔ تفرق کو اختلاف پر اس لیے مقدم کیا گیا کیونکہ یہ اس کے لیے ایک مقدمے کی طرح ہے جو اس کی طرف لے جاتا ہے؛ کیونکہ جب تک لوگ مجتمع اور باہم مربوط رہتے ہیں، ان کے عقائد ایک دوسرے سے جڑے رہتے ہیں اور میل جول و تعامل کے ذریعے متحد رہتے ہیں، اور یہی چیز انہیں اختلاف سے بچاتی ہے۔ لیکن جب وہ تفرق کا شکار ہو کر ایک دوسرے سے کٹ جاتے ہیں، تو یہ چیز انہیں مشرب اور مسلک کے اختلاف کی طرف لے جاتی ہے، اور زیادہ دیر نہیں گزرتی کہ ان کی فکریں اور رائیں ایک دوسرے سے الگ ہو جاتی ہیں، ان میں گروہ بندی ظاہر ہوتی ہے اور وحدت کا شیرازہ بکھر جاتا ہے۔ گویا اللہ تعالیٰ فرما رہا ہے: \"تم ان لوگوں کی طرح نہ ہو جانا جو پہلے جسمانی طور پر تفرق کا شکار ہوئے اور جماعت سے نکل گئے، اور انجام کار اس چیز نے انہیں عقائد اور آراء کے اختلاف تک پہنچا دیا\"۔\n\nاللہ تعالیٰ نے اپنے کلام میں کئی مقامات پر اس اختلاف کی نسبت \"بغی\" (سرکشی) کی طرف دی ہے۔ اللہ تعالیٰ کا فرمان ہے: **وَمَا اخْتَلَفَ فِيهِ إِلَّا الَّذِينَ أُوتُوهُ مِن بَعْدِ مَا جَاءَتْهُمُ الْبَيِّنَاتُ بَغْيًا بَيْنَهُمْ** (اور اس میں اختلاف نہیں کیا مگر انہی لوگوں نے جنہیں وہ دی گئی تھی، ان کے پاس واضح نشانیاں آنے کے بعد، آپس کی سرکشی کی بنا پر) [البقرہ: ۲۱۳]۔ اگرچہ افراد کے درمیان فہم کے فرق کی وجہ سے عقائد اور آراء میں اختلاف کا ظہور ایک فطری امر ہے، لیکن جس طرح اس اختلاف کا ظہور فطری ہے، اسی طرح اس کے دفع کے لیے اجتماع اور اختلاف کرنے والوں کو اتحاد کے میدان کی طرف واپس لانا بھی ضروری ہے۔ پس اختلاف کو ختم کرنا بالواسطہ طور پر ممکن اور مقدور ہے، اور امت کا اس سے اعراض کرنا ان کی سرکشی (بغی) ہے اور خود کو اختلاف کی ہلاکت میں ڈالنا ہے۔\n\nقرآن نے اتحاد کی دعوت پر بہت زور دیا ہے اور اختلاف سے روکنے میں مبالغہ کیا ہے؛ یہ سب اس لیے ہے کہ اس امت کے معاملے میں یہ پیش گوئی تھی کہ یہ بھی اپنے سے پہلے والوں کی طرح اختلاف کریں گے بلکہ ان سے بھی بڑھ جائیں گے۔ پہلے بھی کئی بار یہ بات گزر چکی ہے کہ قرآن کا طریقہ یہ ہے کہ جب وہ کسی چیز سے ڈرانے اور اس کے ارتکاب سے روکنے میں مبالغہ کرے، تو یہ اس کے واقع ہونے اور اس میں مبتلا ہونے کی علامت ہوتی ہے۔ یہ وہ بات ہے جس کی خبر نبی ﷺ نے بھی دی ہے جیسا کہ قرآن نے دی، کہ اختلاف ان کی امت میں سرایت کر جائے گا اور پھر مختلف فرقوں کی صورت میں ظاہر ہوگا، اور ان کی امت ویسے ہی اختلاف کرے گی جیسے ان سے پہلے یہود و نصاریٰ نے کیا تھا۔ اس بارے میں روایات \"بحث روائی\" میں آئیں گی۔\n\nحوادث کے تسلسل نے قرآن کی اس پیش گوئی کی تصدیق کر دی، چنانچہ رسول اللہ ﷺ کے بعد امت میں تفرقہ پیدا ہونے میں دیر نہ لگی اور وہ ٹکڑے ٹکڑے ہو گئے، اور مختلف مذاہب میں اس طرح بٹ گئے کہ صحابہ کے دور سے لے کر آج تک ایک دوسرے کی تکفیر کر رہے ہیں۔ جب بھی کسی نے ان کے درمیان صلح اور موافقت کی کوشش کی، اس سے ایک تیسرا مذہب پیدا ہو گیا۔\n\nتجزیہ و تحلیل کے ذریعے جو بات ہمیں سمجھ آتی ہے وہ یہ ہے کہ اس اختلاف کی اصل جڑ وہ منافقین (المنافقون) ہیں جن کے بارے میں قرآن نے سخت لہجہ اختیار کیا ہے اور ان کے مکر و کید کو بہت بڑا قرار دیا ہے۔ اگر آپ سورہ بقرہ، توبہ، احزاب، منافقون اور دیگر سورتوں میں ان کے بارے میں اللہ کے ارشادات پر غور کریں تو آپ کو حیرت ہوگی۔ رسول اللہ ﷺ کے عہد میں جب تک وحی کا سلسلہ منقطع نہیں ہوا تھا، ان کا یہی حال تھا، پھر جب آپ ﷺ کی وفات ہوئی تو اچانک ان کا ذکر غائب ہو گیا اور ان کی آوازیں تھم گئیں۔\n\n(گویا حجون سے صفا تک کوئی مونس نہ تھا اور نہ مکہ میں کوئی قصہ گو رات کو محفل سجاتا تھا)۔\n\nپھر لوگوں نے دیر نہ کی اور خود کو بکھرا ہوا پایا، مختلف مذاہب نے ان کے درمیان دوریاں پیدا کر دیں، استبدادی اور جابر حکومتوں نے انہیں غلام بنا لیا، اور انہوں نے زندگی کی سعادت کو گمراہی اور بدبختی کی شقاوت سے بدل دیا۔ اللہ ہی مددگار ہے، اور اس کے فضل سے امید ہے کہ وہ ہمیں سورہ برائت (توبہ) کی تفسیر میں اس بحث کو مکمل کرنے کی توفیق عطا فرمائے گا، انشاء اللہ۔\n\n**اللہ تعالیٰ کا فرمان:**\n**يَوْمَ تَبْيَضُّ وُجُوهٌ وَتَسْوَدُّ وُجُوهٌ...**\n**جس دن کچھ چہرے سفید ہوں گے اور کچھ چہرے سیاہ ہوں گے** [جوادی ترجمہ: سورہ آل عمران، آیت ۱۰۶]\n\nچونکہ یہاں مقام نعمت کی ناشکری کا ہے، جو کہ خیانت کے مانند ہے اور ذلت، انفعال اور شرمندگی کا باعث بنتی ہے، اس لیے اللہ سبحانہ نے آخرت کے عذاب کی اقسام میں سے وہ ذکر فرمایا جو تمثیل کے اعتبار سے اس کے مناسب ہے، اور وہ ہے \"چہرے کا سیاہ ہونا\"۔ دنیا میں اس سے مراد انفعال اور شرمندگی وغیرہ لی جاتی ہے، جیسا کہ اللہ تعالیٰ کا یہ فرمان اس کی طرف اشارہ یا دلالت کرتا ہے: **فَأَمَّا الَّذِينَ اسْوَدَّتْ وُجُوهُهُمْ أَكَفَرْتُم بَعْدَ إِيمَانِكُمْ** (پس جن کے چہرے سیاہ ہوں گے، کیا تم نے اپنے ایمان کے بعد کفر کیا؟)۔\n\nاسی طرح اس نعمت کا شکر ادا کرنے والوں کے ثواب میں سے وہ ذکر فرمایا جو شکر کے مناسب ہے، اور وہ ہے \"چہرے کا سفید ہونا\" جس سے دنیا میں خوشنودی اور رضا مراد لی جاتی ہے۔\n\n**اللہ تعالیٰ کا فرمان:**\n**تِلْكَ آيَاتُ اللَّهِ نَتْلُوهَا عَلَيْكَ بِالْحقِّ**\n**یہ اللہ کی آیات ہیں جو ہم آپ کو حق کے ساتھ پڑھ کر سناتے ہیں** [جوادی ترجمہ: سورہ آل عمران، آیت ۱۰۸]\n\nیہاں ظرف (بالحق) کا تعلق \"نتلوها\" سے ہے، اور مراد یہ ہے کہ یہ تلاوت حق ہے، نہ کہ کوئی شیطانی باطل۔ یا اس کا تعلق \"آیات\" سے ہے جس میں صفت کا معنی پایا جاتا ہے، یا یہ کسی مقدر (محذوف) سے متعلق ہے۔ معنی یہ ہے کہ یہ آیات جو اللہ کے ان دو گروہوں (کافرین اور شاکرین) کے ساتھ کیے جانے والے سلوک کو ظاہر کرتی ہیں، حق کے ساتھ ملی ہوئی ہیں اور باطل یا ظلم کے طریقے پر نہیں ہیں۔ یہ توجیہ اس کے بعد آنے والے جملے **وَمَا اللَّهُ يُرِيدُ ظُلْمًا** کے زیادہ موافق ہے۔\n\n**اللہ تعالیٰ کا فرمان:**\n**وَمَا اللَّهُ يُرِيدُ ظُلْمًا لِّلْعَالَمِينَ**\n**اور اللہ عالمین پر کسی طرح کا ظلم نہیں چاہتا ہے** [جوادی ترجمہ: سورہ آل عمران، آیت ۱۰۸]\n\nلفظ \"ظلم\" کا نکرہ ہونا جبکہ وہ نفی کے سیاق میں ہے، استغراق (عمومیت) کا فائدہ دیتا ہے۔ اور \"للعالمین\" کا ظاہر، جو کہ الف لام کے ساتھ جمع ہے، بھی استغراق کا فائدہ دیتا ہے۔ اس بنیاد پر معنی یہ ہے کہ اللہ کسی بھی قسم کے ظلم کا ارادہ نہیں رکھتا جو تمام جہانوں (العالمین) اور تمام گروہوں کے لیے فرض کیا جا سکے۔ اور حقیقت بھی یہی ہے، کیونکہ لوگوں کے درمیان تفرقہ ایک ایسا امر ہے جس کے منحوس اثرات تمام جہانوں اور تمام لوگوں تک پہنچتے ہیں۔\n\n**اللہ تعالیٰ کا فرمان:**\n**وَلِلَّهِ مَا فِي السَّمَاوَاتِ وَمَا فِي الْأَرْضِ ۚ وَإِلَى اللَّهِ تُرْجَعُ الْأُمُورُ**\n**اور اللہ ہی کے لیے ہے جو کچھ آسمانوں میں ہے اور جو کچھ زمین میں ہے اور تمام امور کی بازگشت اللہ ہی کی طرف ہے** [جوادی ترجمہ: سورہ آل عمران، آیت ۱۰۹]\n\nجب اللہ نے یہ ذکر فرمایا کہ وہ ظلم کا ارادہ نہیں رکھتا، تو اس کی علت (وجہ) ایسی بات سے بیان فرمائی جس سے ظلم کے صدور کا وہم ہی زائل ہو جائے۔ چنانچہ ذکر فرمایا کہ اللہ تعالیٰ تمام اشیاء کا تمام جہتوں سے مالک ہے، پس اسے حق حاصل ہے کہ ان میں جیسے چاہے تصرف کرے؛ لہذا اس کے حق میں ایسی چیز میں تصرف کا تصور ہی نہیں کیا جا سکتا جس کا وہ مالک نہ ہو، تاکہ وہ ظلم یا زیادتی کہلائے۔\n\nعلاوہ ازیں، کوئی شخص ظلم کی طرف تب مائل ہوتا ہے جب اسے کوئی ایسی حاجت درپیش ہو جسے وہ اپنی ملکیت سے باہر کی چیز پر زیادتی کیے بغیر پورا نہ کر سکتا ہو، جبکہ اللہ وہ غنی (الغني) ہے جس کے لیے وہ سب کچھ ہے جو آسمانوں اور زمین میں ہے۔ یہ وہ بات ہے جو بعض مفسرین نے کہی ہے، لیکن یہ آیت کے ظاہر سے میل نہیں کھاتی؛ کیونکہ یہ جواب حقیقت میں اللہ تعالیٰ کے غنا (بے نیازی) پر مبنی ہے نہ کہ اس کی ملکیت پر، جبکہ آیت میں ملکیت کا ذکر ہے نہ کہ غنا کا۔ بہرحال، اس کی ملکیت اس بات کی دلیل ہے کہ وہ ظالم نہیں ہے۔\n\nیہاں ایک اور دلیل بھی ہے، اور وہ یہ کہ تمام امور کا مرجع، وہ جو کچھ بھی ہوں، اللہ تعالیٰ ہی کی طرف ہے۔ پس اللہ کے سوا کسی اور کے پاس کوئی امر (اختیار) ہے ہی نہیں کہ اللہ اسے اس سے چھین لے یا اس کے ہاتھ سے نکال لے اور اس میں اپنی مرضی چلائے اور اس طرح ظالم کہلائے۔ یہی وہ نکتہ ہے جس کی طرف اللہ کا یہ قول اشارہ کرتا ہے: **وَإِلَى اللَّهِ تُرْجَعُ الْأُمُورُ**۔\n\nیہ دونوں پہلو، جیسا کہ آپ دیکھ رہے ہیں، ایک دوسرے کے لیے لازم و ملزوم ہیں؛ ایک اس پر مبنی ہے کہ ہر چیز اللہ ہی کی ہے، اور دوسرا اس پر کہ کوئی بھی امر اللہ کے سوا کسی اور کا نہیں ہے۔\n\n**اللہ تعالیٰ کا فرمان:**\n**كُنتُمْ خَيْرَ أُمَّةٍ أُخْرِجَتْ لِلنَّاسِ...**\n**تم بہترین امت ہو جسے لوگوں کے لیے نکالا گیا ہے** [جوادی ترجمہ: سورہ آل عمران، آیت ۱۱۰]\n\nلوگوں کے لیے امت کے \"اخراج\" (نکالنے) سے مراد (واللہ اعلم) اسے ان کے سامنے ظاہر کرنا ہے۔ اس لفظ (الاخراج) کی خوبی یہ ہے کہ اس میں حدوث (پیدا ہونے) اور بننے کا اشارہ پایا جاتا ہے، جیسا کہ اللہ نے فرمایا: **وَالَّذِي أَخْرَجَ الْمَرْعَىٰ** (اور وہ جس نے چارہ نکالا)۔ یہاں خطاب مومنین سے ہے، جو اس بات کا قرینہ ہے کہ \"الناس\" سے مراد عام بنی نوع انسان ہیں۔ فعل \"کنتم\" (تم تھے) کے بارے میں کہا گیا ہے کہ یہ زمانے کے قید سے آزاد ہے۔ لفظ \"امت\" (الامة) کا اطلاق جماعت اور فرد دونوں پر ہوتا ہے کیونکہ وہ ایک مقصد اور ہدف (المقصد) رکھتے ہیں جس کا وہ قصد کرتے ہیں۔ امر بالمعروف اور نہی عن المنکر کے بعد اللہ پر ایمان کا ذکر کرنا، کل کا ذکر جز کے بعد، یا اصل کا ذکر فرع کے بعد کرنے کے قبیل سے ہے۔\n\nپس آیت کا معنی یہ ہے کہ اے گروہِ مسلمین! تم وہ بہترین امت ہو جسے اللہ نے لوگوں کے لیے ان کی ہدایت کی خاطر ظاہر کیا، کیونکہ تم بحیثیتِ مجموعی اللہ پر ایمان رکھتے ہو اور امر بالمعروف و نہی عن المنکر کے دو فرائض انجام دیتے ہو۔ یہ معلوم ہے کہ اس اعزاز کا پوری امت پر پھیلاؤ اس لیے ہے کہ ان میں سے بعض ایمان کی حقیقت سے متصف ہیں اور امر بالمعروف و نہی عن المنکر کا حق ادا کر رہے ہیں۔ اس مقام پر مفسرین کے کلام کا خلاصہ یہی ہے۔\n\nظاہر یہ ہے (واللہ اعلم) کہ \"کنتم\" زمانے کی قید سے آزاد نہیں ہے، اور یہ آیت اسلام کے ابتدائی ظہور کے وقت ان مومنین کے حال کی مدح کر رہی ہے جو مہاجرین و انصار میں سے سابقینِ اولین تھے۔ یہاں ایمان سے مراد حبل اللہ سے متمسک ہونے اور تفرقہ نہ کرنے کے لیے اجتماعی دعوت پر ایمان لانا ہے، اس کے مقابلے میں جو اس سے پہلے کفر کا ذکر ہوا: **أَكَفَرْتُم بَعْدَ إِيمَانِكُمْ**۔ اسی طرح اہل کتاب کے ایمان سے مراد بھی یہی ہے۔ پس معنی یہ نکلتا ہے کہ اے امتِ اسلام! تم اپنی تشکیل اور لوگوں کے سامنے ظہور کے آغاز میں وہ بہترین امت تھے جو ظاہر ہوئی، کیونکہ تم نیکی کا حکم دیتے تھے، برائی سے روکتے تھے اور ایک جان ہو کر متحد و متفق ہو کر حبل اللہ سے متمسک تھے۔ اگر اہل کتاب بھی اسی صفت پر ہوتے تو ان کے لیے بہتر ہوتا، لیکن انہوں نے اختلاف کیا، ان میں سے کچھ مومن ہیں اور ان کی اکثریت فاسق ہے۔\n\nواضح رہے کہ ان آیات میں غائب سے خطاب کی طرف، اور جمع کے خطاب سے مفرد کے خطاب کی طرف اور اس کے برعکس التفات (الالتفات) کی کئی مثالیں موجود ہیں۔ اسی طرح ضمیر کی جگہ اسمِ ظاہر لانے کی مثالیں بھی ہیں جیسے لفظِ جلالہ کا کئی مقامات پر تکرار۔ ان تمام باتوں کا نکتہ غور کرنے والے پر ظاہر ہے۔\n\n## (بحث روائی)\n\n\"المعانی\" اور \"تفسیر عیاشی\" میں ابوبصیر سے روایت ہے، وہ کہتے ہیں: میں نے ابوعبداللہ علیہ السلام سے اللہ عزوجل کے اس قول: **اتَّقُوا اللَّهَ حَقَّ تُقَاتِهِ** کے بارے میں پوچھا، تو آپؑ نے فرمایا: \"اس کی اطاعت کی جائے تو نافرمانی نہ ہو، اسے یاد رکھا جائے تو بھلایا نہ جائے، اور اس کا شکر ادا کیا جائے تو ناشکری نہ ہو\"۔\n\n\"الدر المنثور\" میں حاکم اور ابن مردویہ نے ایک اور طریق سے ابن مسعود سے روایت کی ہے، وہ کہتے ہیں: رسول اللہ ﷺ نے فرمایا: \"**اتَّقُوا اللَّهَ حَقَّ تُقَاتِهِ** یہ ہے کہ اس کی اطاعت کی جائے تو نافرمانی نہ ہو، اور اسے یاد رکھا جائے تو بھلایا نہ جائے\"۔\n\nاسی کتاب میں خطیب نے انس سے روایت کی ہے، وہ کہتے ہیں: رسول اللہ ﷺ نے فرمایا: \"کوئی بندہ اللہ کا ویسا تقویٰ اختیار نہیں کر سکتا جیسا کہ اس کا حق ہے، یہاں تک کہ وہ یہ جان لے کہ جو اسے پہنچا وہ اس سے چوکنے والا نہ تھا، اور جو اس سے چوک گیا وہ اسے پہنچنے والا نہ تھا\"۔\n\n**میں کہتا ہوں:** پچھلے بیان میں یہ گزر چکا ہے کہ پہلی دو حدیثوں کا معنی آیت سے کس طرح حاصل ہوتا ہے۔ رہی تیسری حدیث، تو وہ لازمِ معنی کے ذریعے تفسیر ہے، اور یہ ظاہر ہے۔\n\n\"تفسیر البرہان\" میں ابن شہر آشوب نے \"تفسیر وکیع\" کے حوالے سے عبدِ خیر سے روایت کی ہے، وہ کہتے ہیں: میں نے علی بن ابی طالب علیہ السلام سے اس قول: **يَا أَيُّهَا الَّذِينَ آمَنُوا اتَّقُوا اللَّهَ حَقَّ تُقَاتِهِ** کے بارے میں پوچھا، تو آپؑ نے فرمایا: \"خدا کی قسم! رسول اللہ ﷺ کے اہل بیت کے سوا کسی نے اس پر عمل نہیں کیا۔ ہم ہی ہیں جنہوں نے اسے یاد رکھا اور کبھی نہیں بھولے، ہم ہی ہیں جنہوں نے اس کا شکر ادا کیا اور کبھی ناشکری نہیں کی، اور ہم ہی ہیں جنہوں نے اس کی اطاعت کی اور کبھی نافرمانی نہیں کی\"۔ جب یہ آیت نازل ہوئی تو صحابہ نے کہا کہ ہم اس کی طاقت نہیں رکھتے، تب اللہ نے نازل فرمایا: **فَاتَّقُوا اللَّهَ مَا اسْتَطَعْتُمْ**۔ وکیع کہتے ہیں: یعنی جتنا تم سے ہو سکے۔\n\n\"تفسیر عیاشی\" میں ابوبصیر سے روایت ہے، وہ کہتے ہیں: میں نے ابوعبداللہ علیہ السلام سے اللہ کے قول: **اتَّقُوا اللَّهَ حَقَّ تُقَاتِهِ** کے بارے میں پوچھا، تو آپؑ نے فرمایا: \"یہ منسوخ ہے\"۔ میں نے پوچھا: \"اسے کس چیز نے منسوخ کیا؟\" فرمایا: \"اللہ کے اس قول نے: **فَاتَّقُوا اللَّهَ مَا اسْتَطَعْتُمْ**\"۔\n\n**میں کہتا ہوں:** وکیع کی روایت سے یہ فائدہ حاصل ہوتا ہے کہ عیاشی کی روایت میں \"نسخ\" سے مراد تقویٰ کے مراتب کا بیان ہے۔ رہا نسخ اپنے اصطلاحی معنی میں، جیسا کہ بعض مفسرین سے نقل کیا گیا ہے، تو یہ وہ معنی ہے جسے ظاہرِ کتاب رد کرتا ہے۔\n\n\"المجمع\" میں امام صادق علیہ السلام سے اس آیت کے بارے میں روایت ہے کہ آپؑ نے **مُسَلِّمُونَ** (تشدید کے ساتھ) پڑھا ہے۔\n\n\"الدر المنثور\" میں اللہ تعالیٰ کے قول: **وَاعْتَصِمُوا بِحَبْلِ اللَّهِ جَمِيعًا** کے بارے میں ابن ابی شیبہ اور ابن جریر نے ابوسعید خدری سے روایت کی ہے، وہ کہتے ہیں: رسول اللہ ﷺ نے فرمایا: \"اللہ کی کتاب ہی اللہ کی وہ رسی ہے جو آسمان سے زمین تک تنی ہوئی ہے\"۔\n\nاسی میں ابن ابی شیبہ نے ابوشریح خزاعی سے روایت کی ہے، وہ کہتے ہیں: رسول اللہ ﷺ نے فرمایا: \"یہ قرآن ایک سبب (ذریعہ) ہے جس کا ایک سرا اللہ کے ہاتھ میں ہے اور دوسرا سرا تمہارے ہاتھوں میں، پس اسے مضبوطی سے تھامے رکھو، کیونکہ اس کے بعد تم کبھی ہلاک نہیں ہو گے اور نہ کبھی گمراہ ہو گے\"۔\n\n\"المعانی\" میں امام سجاد علیہ السلام سے ایک حدیث میں مروی ہے: \"اور حبل اللہ قرآن ہے\"۔\n\n**میں کہتا ہوں:** اس معنی میں فریقین کے طریقوں سے اور بھی روایات موجود ہیں۔\n\n\"تفسیر عیاشی\" میں امام باقر علیہ السلام سے مروی ہے: \"آلِ محمد ہی اللہ کی وہ رسی ہیں جس سے متمسک ہونے کا حکم دیا گیا ہے، چنانچہ فرمایا: **وَاعْتَصِمُوا بِحَبْلِ اللَّهِ جَمِيعًا وَلَا تَفَرَّقُوا**\"۔\n\n**میں کہتا ہوں:** اس معنی میں دیگر روایات بھی ہیں؛ اور پہلے بیان میں وہ باتیں گزر چکی ہیں جن سے ان کے معنی کی تائید ہوتی ہے، اور آنے والی روایات بھی ان کی تائید کرتی ہیں۔\n\n\"الدر المنثور\" میں طبرانی نے زید بن ارقم سے روایت کی ہے، وہ کہتے ہیں: رسول اللہ ﷺ نے فرمایا: \"میں تم سے پہلے (حوض پر) پہنچنے والا ہوں، اور تم حوض پر میرے پاس وارد ہو گے، پس دیکھنا کہ تم ثقلین (دو گراں قدر چیزوں) میں میرے بعد کیا رویہ اختیار کرتے ہو؟\" پوچھا گیا: \"اے اللہ کے رسول! ثقلین کیا ہیں؟\" فرمایا: \"بڑی چیز اللہ عزوجل کی کتاب ہے، وہ ایک ذریعہ ہے جس کا ایک سرا اللہ کے ہاتھ میں ہے اور دوسرا تمہارے ہاتھوں میں، پس اسے تھامے رکھو، تم کبھی نہیں بھٹکو گے اور نہ گمراہ ہو گے؛ اور چھوٹی چیز میری عترت ہے، اور یہ دونوں ہرگز ایک دوسرے سے جدا نہیں ہوں گے یہاں تک کہ حوض پر میرے پاس وارد ہوں۔ میں نے اپنے رب سے ان دونوں کے لیے یہی مانگا ہے، پس ان سے آگے نہ بڑھنا ورنہ ہلاک ہو جاؤ گے، اور انہیں سکھانے کی کوشش نہ کرنا کیونکہ وہ تم سے زیادہ جانتے ہیں\"۔\n\n**میں کہتا ہوں:** حدیثِ ثقلین ان متواتر احادیث میں سے ہے جن کی روایت پر فریقین کا اجماع ہے؛ سورہ کے آغاز میں یہ بات گزر چکی ہے کہ بعض علمائے حدیث نے اس کے راوی صحابہ کی تعداد ۳۵ تک پہنچائی ہے جن میں مرد اور خواتین دونوں شامل ہیں؛ اور ان سے راویوں اور اہل حدیث کی ایک بہت بڑی جماعت نے اسے روایت کیا ہے۔\n\n\"الدر المنثور\" ہی میں ابن ماجہ، ابن جریر اور ابن ابی حاتم نے انس سے روایت کی ہے، وہ کہتے ہیں: رسول اللہ ﷺ نے فرمایا: \"بنی اسرائیل اکہتر (۷۱) فرقوں میں بٹ گئے تھے، اور میری امت بہتر (۷۲) فرقوں میں بٹ جائے گی، وہ سب آگ میں ہوں گے سوائے ایک کے\"۔ انہوں نے پوچھا: \"اے اللہ کے رسول! وہ ایک کون سا ہے؟\" فرمایا: \"الجماعۃ\" (جماعت)۔ پھر آپ ﷺ نے پڑھا: **وَاعْتَصِمُوا بِحَبْلِ اللَّهِ جَمِيعًا**۔\n\n**میں کہتا ہوں:** یہ روایت بھی مشہورات میں سے ہے، اور شیعہ نے اسے ایک اور انداز سے روایت کیا ہے جیسا کہ \"الخصال\"، \"المعانی\"، \"الاحتجاج\"، \"الامالی\"، \"کتاب سلیم بن قیس\" اور \"تفسیر عیاشی\" میں ہے۔ \"الخصال\" کے الفاظ اپنی سند کے ساتھ سلیمان بن مہران سے، انہوں نے جعفر بن محمد (امام صادقؑ) سے، انہوں نے اپنے آبا و اجداد سے، انہوں نے امیر المومنین علیہ السلام سے روایت کی ہے، آپؑ نے فرمایا: \"میں نے رسول اللہ ﷺ کو فرماتے سنا: موسیٰ کی امت ان کے بعد اکہتر فرقوں میں بٹ گئی، جن میں سے ایک فرقہ ناجی (نجات پانے والا) ہے اور ستر آگ میں ہیں۔ عیسیٰ کی امت ان کے بعد بہتر فرقوں میں بٹ گئی، جن میں سے ایک ناجی ہے اور اکہتر آگ میں ہیں۔ اور میری امت میرے بعد تہتر (۷۳) فرقوں میں بٹ جائے گی، جن میں سے ایک ناجی ہوگا اور بہتر آگ میں ہوں گے\"۔\n\n**میں کہتا ہوں:** یہی وہ روایت ہے جو آنے والی باتوں کے موافق ہے۔\n\n\"الدر المنثور\" میں ابوداؤد، ترمذی، ابن ماجہ اور حاکم نے (اور اسے صحیح قرار دیا) ابوہریرہ سے روایت کی ہے، وہ کہتے ہیں: رسول اللہ ﷺ نے فرمایا: \"یہود اکہتر فرقوں میں بٹے، اور نصاریٰ بہتر فرقوں میں؛ اور میری امت تہتر فرقوں میں بٹ جائے گی\"۔\n\n**میں کہتا ہوں:** یہ معنی دیگر طریقوں سے معاویہ اور دیگر سے بھی مروی ہے۔\n\nاسی میں حاکم نے عبداللہ بن عمر سے روایت کی ہے، وہ کہتے ہیں: رسول اللہ ﷺ نے فرمایا: \"میری امت پر وہی کچھ آئے گا جو بنی اسرائیل پر آیا، بالکل ویسے ہی جیسے ایک جوتا دوسرے جوتے کے برابر ہوتا ہے، یہاں تک کہ اگر ان میں سے کسی نے اپنی ماں کے ساتھ اعلانیہ نکاح کیا ہوگا تو میری امت میں بھی ویسا کرنے والا ہوگا۔ بنی اسرائیل اکہتر ملتوں میں بٹ گئے تھے، اور میری امت تہتر ملتوں میں بٹ جائے گی، وہ سب آگ میں ہوں گی سوائے ایک ملت کے\"۔ آپ ﷺ سے پوچھا گیا: \"وہ ایک کون سی ہے؟\" فرمایا: \"جس پر آج میں اور میرے اصحاب ہیں\"۔\n\n**میں کہتا ہوں:** ابن اثیر کی \"جامع الاصول\" میں ترمذی کے حوالے سے ابن عمرو بن عاص سے نبی ﷺ سے اسی طرح مروی ہے۔\n\n\"کمال الدین\" میں اپنی سند کے ساتھ غیاث بن ابراہیم سے، انہوں نے امام صادقؑ سے، انہوں نے اپنے آبا و اجداد سے روایت کی ہے کہ رسول اللہ ﷺ نے فرمایا: \"جو کچھ گزشتہ امتوں میں ہوا، اس امت میں بھی بعینہٖ ویسا ہی ہوگا، جیسے ایک جوتا دوسرے جوتے کے برابر اور ایک تیر کا پر دوسرے پر کے برابر ہوتا ہے\"۔\n\n\"تفسیر قمی\" میں نبی ﷺ سے مروی ہے: \"تم ضرور اپنے سے پہلے والوں کی سنت (طریقے) پر چلو گے، بالکل ویسے ہی جیسے ایک جوتا دوسرے جوتے کے برابر اور ایک تیر کا پر دوسرے پر کے برابر ہوتا ہے۔ تم ان کے راستے سے نہیں چوکو گے اور نہ وہ تم سے چوکے گا؛ بالشت بالشت کے برابر، ہاتھ ہاتھ کے برابر اور گز گز کے برابر، یہاں تک کہ اگر تم سے پہلے والے کسی گوہ کے سوراخ میں داخل ہوئے ہوں گے تو تم بھی اس میں داخل ہو جاؤ گے\"۔ انہوں نے پوچھا: \"اے اللہ کے رسول! کیا آپ کی مراد یہود و نصاریٰ ہیں؟\" فرمایا: \"تو اور کون مراد ہے؟ تم اسلام کے کڑوں کو ایک ایک کر کے توڑ دو گے، تمہارے دین میں سب سے پہلے جو چیز ٹوٹے گی وہ امانت ہے اور سب سے آخر میں نماز\"۔\n\n\"جامع الاصول\" میں صحاح سے جو کچھ نکالا گیا ہے اس میں، اور \"صحیح ترمذی\" میں نبی ﷺ سے مروی ہے کہ آپ ﷺ نے فرمایا: \"اس ذات کی قسم جس کے ہاتھ میں میری جان ہے! تم ضرور اپنے سے پہلے والوں کے طریقوں پر چلو گے (اور رزین نے اضافہ کیا) بالکل ویسے ہی جیسے ایک جوتا دوسرے جوتے کے برابر اور ایک تیر کا پر دوسرے پر کے برابر ہوتا ہے، یہاں تک کہ اگر ان میں کوئی ایسا تھا جس نے اپنی ماں کے ساتھ (بدکاری) کی تو تم میں بھی ایسا ہوگا، اب مجھے نہیں معلوم کہ تم بچھڑے کی پوجا کرو گے یا نہیں؟\"\n\n**میں کہتا ہوں:** یہ روایت بھی مشہورات میں سے ہے، اسے اہل سنت نے اپنی صحاح اور دیگر کتب میں روایت کیا ہے، اور شیعہ نے اپنی جوامع میں۔\n\n\"صحیحین\" (بخاری و مسلم) میں انس سے مروی ہے کہ رسول اللہ ﷺ نے فرمایا: \"میرے اصحاب میں سے کچھ لوگ حوض پر میرے پاس وارد ہوں گے، یہاں تک کہ جب وہ میرے سامنے لائے جائیں گے تو انہیں مجھ سے دور کھینچ لیا جائے گا۔ میں کہوں گا: اے میرے رب! یہ تو میرے اصحاب ہیں! تو مجھ سے کہا جائے گا: آپ نہیں جانتے کہ انہوں نے آپ کے بعد کیا کیا بدعتیں ایجاد کیں\"۔\n\n\"صحیحین\" ہی میں ابوہریرہ سے مروی ہے کہ رسول اللہ ﷺ نے فرمایا: \"قیامت کے دن میرے اصحاب کی ایک جماعت — یا فرمایا میری امت کی — میرے پاس حوض پر آئے گی، تو انہیں حوض سے دور ہٹا دیا جائے گا۔ میں کہوں گا: اے رب! یہ میرے اصحاب ہیں! تو وہ فرمائے گا: آپ کو علم نہیں کہ انہوں نے آپ کے بعد کیا کیا نئی چیزیں نکالیں، وہ اپنی ایڑیوں کے بل الٹے پھر گئے تھے، پس انہیں دور ہٹا دیا جائے گا\"۔\n\n**میں کہتا ہوں:** یہ حدیث بھی مشہورات میں سے ہے؛ اسے فریقین نے اپنی صحاح اور جوامع میں کئی صحابہ جیسے ابن مسعود، انس، سہل بن ساعد، ابوہریرہ، ابوسعید خدری، عائشہ، ام سلمہ، اسماء بنت ابی بکر اور دیگر سے، اور بعض ائمہ اہل بیت علیہم السلام سے روایت کیا ہے۔\n\nیہ روایات اپنی کثرت اور تنوع کے باوجود اس بات کی تصدیق کرتی ہیں جو ہم نے آیاتِ کریمہ کے ظاہر سے سمجھا ہے، اور حوادث و فتنوں کے تسلسل نے ان روایات کی تصدیق کر دی ہے۔\n\n\"الدر المنثور\" میں حاکم نے روایت کی اور اسے صحیح قرار دیا کہ ابن عمر سے مروی ہے کہ رسول اللہ ﷺ نے فرمایا: \"جو جماعت سے ایک بالشت کے برابر بھی نکلا، اس نے اسلام کا پٹہ اپنی گردن سے اتار پھینکا یہاں تک کہ وہ واپس لوٹ آئے، اور جو اس حال میں مرا کہ اس پر جماعت کا کوئی امام نہ تھا، تو اس کی موت جاہلیت کی موت ہے\"۔\n\n**میں کہتا ہوں:** یہ روایت بھی مضمون کے اعتبار سے مشہورات میں سے ہے؛ فریقین نے آپ ﷺ سے روایت کی ہے کہ آپ ﷺ نے فرمایا: \"جو اس حال میں مرا کہ اس نے اپنے زمانے کے امام کو نہ پہچانا، وہ جاہلیت کی موت مرا\"۔\n\n\"جامع الاصول\" میں ترمذی اور سنن ابی داؤد سے نبی ﷺ سے مروی ہے: \"میری امت کا ایک گروہ ہمیشہ حق پر قائم رہے گا\"۔\n\n\"المجمع\" میں اللہ تعالیٰ کے قول: **أَكَفَرْتُم بَعْدَ إِيمَانِكُمْ** کے بارے میں امیر المومنین علیہ السلام سے مروی ہے کہ \"یہ اس امت کے بدعتی اور باطل خواہشات و آراء والے لوگ ہیں\"۔\n\nاسی کتاب میں اور \"تفسیر عیاشی\" میں اللہ کے قول: **كُنتُمْ خَيْرَ أُمَّةٍ أُخْرِجَتْ لِلنَّاسِ** کے بارے میں ابوعمرو زبیری سے، انہوں نے امام صادق علیہ السلام سے روایت کی ہے، آپؑ نے فرمایا: \"اس سے مراد وہ امت ہے جس کے لیے ابراہیمؑ کی دعا واجب ہوئی؛ یہ وہ امت ہے جس میں اللہ نے (رسول) بھیجا، اور جس سے اور جس کی طرف بھیجا؛ یہی امتِ وسطیٰ ہے، اور یہی وہ بہترین امت ہے جو لوگوں کے لیے ظاہر کی گئی\"۔\n\n**میں کہتا ہوں:** اس روایت کے معنی کی وضاحت اللہ تعالیٰ کے اس قول: **وَمِن ذُرِّيَّتِنَا أُمَّةً مُّسْلِمَةً لَّكَ** [البقرہ: ۱۲۸] کی تفسیر میں گزر چکی ہے۔\n\n\"الدر المنثور\" میں ابن ابی حاتم نے ابوجعفر (امام باقرؑ) سے روایت کی ہے کہ **كُنتُمْ خَيْرَ أُمَّةٍ أُخْرِجَتْ لِلنَّاسِ** سے مراد \"نبی ﷺ کے اہل بیت علیہم السلام ہیں\"۔\n\nاسی میں احمد نے حسن سند کے ساتھ علی علیہ السلام سے روایت کی ہے، آپؑ نے فرمایا: رسول اللہ ﷺ نے فرمایا: \"مجھے وہ کچھ دیا گیا جو انبیاء میں سے کسی کو نہیں دیا گیا: رعب کے ذریعے میری مدد کی گئی، مجھے زمین کی کنجیاں دی گئیں، میرا نام احمد رکھا گیا، مٹی کو میرے لیے پاک کرنے والی (طہور) بنایا گیا، اور میری امت کو بہترین امت بنایا گیا\"۔"}