{"edition":"almizan_fa","name":"تفسیر المیزان","author":"Allamah Muhammad Husayn Tabatabai","language":"fa","text":"****\n\n\n## [سوره الأنعام (6):آيات 19 تا 20]\n\n\n<span id=\"surah-6-ayah-19\"></span>\n```arabic\nقُلْ أَىُّ شَىْءٍ أَكْبَرُ شَهَـٰدَةً ۖ قُلِ ٱللَّهُ ۖ شَهِيدٌۢ بَيْنِى وَبَيْنَكُمْ ۚ وَأُوحِىَ إِلَىَّ هَـٰذَا ٱلْقُرْءَانُ لِأُنذِرَكُم بِهِۦ وَمَنۢ بَلَغَ ۚ أَئِنَّكُمْ لَتَشْهَدُونَ أَنَّ مَعَ ٱللَّهِ ءَالِهَةً أُخْرَىٰ ۚ قُل لَّآ أَشْهَدُ ۚ قُلْ إِنَّمَا هُوَ إِلَـٰهٌ وَٰحِدٌ وَإِنَّنِى بَرِىٓءٌ مِّمَّا تُشْرِكُونَ (١٩)\n```\n\n\n<span id=\"surah-6-ayah-20\"></span>\n```arabic\nٱلَّذِينَ ءَاتَيْنَـٰهُمُ ٱلْكِتَـٰبَ يَعْرِفُونَهُۥ كَمَا يَعْرِفُونَ أَبْنَآءَهُمُ ۘ ٱلَّذِينَ خَسِرُوٓا۟ أَنفُسَهُمْ فَهُمْ لَا يُؤْمِنُونَ (٢٠)\n```\n\n\n### ترجمه آيات‏\n\n\n```farsi\n(به اين كفار) بگو: چه چيزى در شهادت بزرگتر است (تا من او را براى شما گواه بر رسالت خود بياورم؟) بگو خداى تعالى گواه بين من و شما است، و اين قرآن به من وحى شده كه شما و هر كه را كه اين قرآن به گوشش بخورد انذار كرده، هشدار دهم آيا (با چنين گواهى بزرگ) باز هم شما شهادت مى‏دهيد كه با خداى تعالى خدايان ديگرى هست؟ بگو من كه چنين شهادتى نمى‏دهم، بگو حق مطلب همين است كه او معبودى است يگانه و به درستى كه من از هر چه كه شما شريك خدايش پنداشته‏ايد بيزارم (19).\nآنان كه ما كتابشان داديم رسول اللَه را مى‏شناسند همانطورى كه فرزندان خود را مى‏شناسند، و كسانى كه به نفس خود زيان كرده‏اند ايمان نمى‏آورند (20).\n```\n\n\n### بيان آيات‏\n\nاين آيات احتجاج مى‏كند بر مساله وحدانيت خداى تعالى از راه وحى. و حال آنكه اين مساله عقلى و از مسائلى است كه عقل از طرق مختلفى به آن راه دارد، و ليكن صرف اين\n\nجهت باعث نمى‏شود كه نتوان آن را از طريق وحى صريح قطعى هم اثبات نمود، مگر غرض از برهان عقلى، جز تحصيل يقين چيز ديگرى است؟ وقتى غرض از آن تحصيل يقين به وحدانيت خدا باشد و بر حسب فرض، وحى الهى هم قطعى و غير قابل ترديد باشد چه مانعى دارد كه همان وحى برهان بر وحدانيت خدا قرار گيرد آنهم وحيى چون قرآن كه اساسش متكى بر تحدى است‏.\n\n﴿قُلْ أَيُّ شَيْ‏ءٍ أَكْبَرُ شَهَادَةً قُلِ اَللَّهُ شَهِيدٌ بَيْنِي وَ بَيْنَكُمْ﴾\n\nرسول گرامى خود را دستور مى‏دهد كه از مشركين بپرسد چه چيزى از هر چيز در مساله شهادت بزرگتر است؟ البته بايد دانست كه مراد از اين «شهادت» اعم از تحمل آن از راه حس و مشاهده و از اداى آن است، و چون تحمل و اداى شهادت مخصوصا تحمل آن، از چيزهايى است كه بر حسب اختلاف درجه فهم متحملين و وضوح و پيچيدگى وقايع و قوت و ضعف بيان بيان كننده آن، مختلف مى‏شود، و مسلما متحملى كه سهو و نسيان و غفلت بر مزاجش غلبه دارد، مانند متحملى كه هر چه بشنود و ببيند حفظ مى‏كند، نيست، و مست همانند هوشيار و بيگانه به مثل آشناى به جزئيات واقعه نيست، از اين رو بايد بدون ترديد گفت: خداى تعالى در تحمل شهادت و خبر يافتن از وقايع جهان و افعال بندگان از هر خبردارى خبردارتر است، چون او است كه بزرگ و كوچك اشياء را آفريده، و اختراع و ايجاد هر چيز منتهى به او مى‏باشد با هر چيز، و محيط بر هر چيز است، حتى به سنگينى ذره‏اى كه در آسمان‌ها و زمين است، و كوچكتر از ذره و بزرگتر از آن علم او مخفى نبوده و او فراموش و گمش نمى‏كند. و از آنجايى كه پاسخ اين سؤال خيلى روشن بود لذا در آيه متعرض آن نشد و نيازى نديد به اينكه در جواب گفته شود: «قل اللَه اكبر شهادة» همانطورى كه در آيه‏ ﴿قُلْ لِمَنْ مَا فِي اَلسَّمَاوَاتِ وَ اَلْأَرْضِ﴾ از قول مخاطبين فرمود: ﴿قُلْ لِلَّهِ﴾ و يا گفته شود «سيقولون اللَه - خواهند گفت خدا» همانطورى كه در آيه‏ ﴿قُلْ لِمَنِ اَلْأَرْضُ وَ مَنْ فِيهَا إِنْ كُنْتُمْ تَعْلَمُونَ﴾ فرمود: ﴿سَيَقُولُونَ لِلَّهِ﴾ اعتراف خواهند كرد به اينكه زمين و هر كس كه در او است از آن خدا است.\n\nعلاوه بر اينكه جمله‏ ﴿قُلِ اَللَّهُ شَهِيدٌ بَيْنِي وَ بَيْنَكُمْ﴾ خود دلالت بر جواب هم دارد و در حقيقت قائم مقام همان جواب است.\n\nبعيد هم نيست كه كلمه «شهيد» خبر باشد از مبتداى محذوف، و آن مبتدا ضميرى باشد كه به كلمه «اللَه» برگشته و تقديرش چنين باشد: «قل اللَه هو شهيد بينى و بينكم» كه در اين صورت جمله مذكور هم جواب از آن سؤال خواهد بود، و هم شروع در مطلبى ديگر.\n\nاين نكته را نيز نبايد از نظر دور داشت كه جمله‏ ﴿قُلِ اَللَّهُ شَهِيدٌ بَيْنِي وَ بَيْنَكُمْ﴾ علاوه بر اينكه مشتمل است بر اخبار رسول خدا (صلى الله عليه وآله و سلم) از اينكه خداوند شهيد است، خود شهادت جداگانه‏اى هم هست، براى اينكه كلمه «قل» مى‏رساند كه خدا به او فرموده كه مشركين را به شهادتش خبر دهد، و اين معنا بدون شهادت خدا بر نبوت او صحيح نيست، بنابراین جمله مذكور هم دلالت دارد بر شهادت خدا نسبت به هر چيز و هم بر شهادتش نسبت به نبوت رسول خدا (صلى الله عليه وآله و سلم) و با اين حال ديگر حاجتى نيست به اينكه در اينجا به منظور شهادت به نبوت آن جناب كلام جداگانه‏اى تصريحا، نظير: ﴿وَ اَللَّهُ يَعْلَمُ إِنَّكَ لَرَسُولُهُ﴾ و يا تلويحا، نظير: ﴿لَكِنِ اَللَّهُ يَشْهَدُ بِمَا أَنْزَلَ إِلَيْكَ أَنْزَلَهُ بِعِلْمِهِ﴾ ايراد بفرمايد.\n\nو اينكه شهادت را مقيد كرد به‏ ﴿بَيْنِي وَ بَيْنَكُمْ﴾ دلالت مى‏كند بر اينكه خداى تعالى بين پيغمبر اكرم و قومش كه دو طرف خصومتند واسطه است، و چون مى‏دانيم كه خصومت و طرفيت آن جناب با قومش تنها بر سر مساله نبوت و رسالت و ادعاى نزول قرآن است كه بعدا با جمله‏ ﴿وَ أُوحِيَ إِلَيَّ هَذَا اَلْقُرْآنُ﴾ طرح مى‏شود، از اين جهت مى‏فهميم كه مراد از شهادت خدا بين او و قومش همان گواهى بر نبوت اوست، چنان كه جمله‏ ﴿اَلَّذِينَ آتَيْنَاهُمُ اَلْكِتَابَ يَعْرِفُونَهُ كَمَا يَعْرِفُونَ أَبْنَاءَهُمُ﴾ هم به طورى كه بعدا خواهيم گفت اين دلالت را تاييد مى‏نمايد.\n\n\n#### انذار و تخويف، در دعوت نبوت مؤثرتر از تبشير و تطميع بوده است‏\n\n﴿وَ أُوحِيَ إِلَيَّ هَذَا اَلْقُرْآنُ لِأُنْذِرَكُمْ بِهِ وَ مَنْ بَلَغَ﴾\n\nحكايت قسمتى از بياناتى است كه رسول خدا بايد آن را براى مشركين ايراد فرمايد و اين جمله عطف به‏ ﴿اَللَّهُ شَهِيدٌ...﴾ است در اين آيه مساله انذار و هشدار غايت و نتيجه نزول قرآن كريم قرار گرفته، دعوت نبوت از طريق تخويف آغاز گشته، و اين خود در فهم عامه مردم مؤثرتر از تطميع است.\n\nبراى اينكه گر چه تطميع و اميدوار ساختن مردم نيز راهى است براى دعوت انبيا و قرآن\n\nعزيز هم تا اندازه‏اى اين طريقه را به كار برده، ليكن اصولا اميدوارى آدمى را به طور الزام وادار به طلب نمى‏كند، و بيش از ايجاد شوق و رغبت در آدمى، اثر ندارد، به خلاف تخويف و تهديد كه به حكم عقلى وجوب دفع ضرر احتمالى، احتراز از آنچه تهديد به آن شده واجب و آدمى به دفع آن ملزم مى‏شود.\n\nعلاوه بر اين، اگر مردم در گمراهى خود هيچ گونه تقصيرى نمى‏داشتند، مناسب بود كه دعوت الهى از راه تطميع آغاز گردد، ليكن مردم در گمراهى خود مقصر هستند، براى اينكه دعوت اسلام، دعوت به دين فطرت، يعنى به دينى است كه سرچشمه‏اش در نهاد خود بشر است، و اين خود او است كه با دست خويش و با ارتكاب شرك و گناه، فطرت خود را پشت سر افكنده و شقاوت را بر دل خود چيره نموده و در نتيجه دچار سخط الهى شده است، و چون چنين است حزم و حكمت اقتضا مى‏كند كه دعوت آنان از راه انذار و هشدار آغاز گردد، و براى همين جهت بوده كه در آيات بسيارى وظيفه آن جناب منحصر در انذار شده است، مانند آيه: ﴿إِنْ أَنْتَ إِلاَّ نَذِيرٌ﴾ و آيه: ﴿وَ إِنَّمَا أَنَا نَذِيرٌ مُبِينٌ﴾.\n\nالبته اين مطلب، كه گفته شد، در باره مردم عامى است، و اما خواص از مردم، يعنى آنان كه خداى را از روى محبتى كه به او دارند عبادت مى‏كنند، نه از جهت ترس از آتش و يا طمع در بهشت، البته از خوف و رجا و تهديد و تطميعى كه در دعوت دينى هست چيز ديگرى تلقى مى‏كنند، وقتى به تهديد از آتش برمى‏خورند از آن آتش، آتش فراق و دورى از پروردگار و سخط وى را مى‏فهمند، و همچنين از شنيدن وصف بهشت به نعمت وصل و قرب ساحت او و خشنودى او منتقل شده و مشتاق آن مى‏گردند.\n\n\n#### جمله: ﴿لِأُنْذِرَكُمْ بِهِ وَ مَنْ بَلَغَ﴾ شاهد بر ابدى و جهانى بودن رسالت پيامبر اسلام (صلى الله عليه وآله و سلم) مى‏باشد\n\nاز ظاهر ﴿لِأُنْذِرَكُمْ بِهِ وَ مَنْ بَلَغَ﴾ گر چه برمى‏آيد كه خطابش به مشركين مكه و يا عموم قريش و يا جميع عرب است، الا اينكه مقابله بين «كم» و بين «من بلغ» البته با حفظ اين جهت كه مراد از «من بلغ» كسانى باشند كه مطالب را از خود پيغمبر نشنيده‏اند، چه معاصرين و چه مردمى كه بعد از عصر آن جناب به وجود مى‏آيند - دلالت دارد بر اينكه مقصود از ضمير خطاب «كم» در جمله‏ ﴿لِأُنْذِرَكُمْ بِهِ﴾ كسانى هستند كه پيغمبر اكرم ايشان را پيش از نزول آيه يا مقارن يا پس از نزول انذار مى‏فرمود.\n\nپس اينكه فرمود: ﴿وَ أُوحِيَ إِلَيَّ هَذَا اَلْقُرْآنُ لِأُنْذِرَكُمْ بِهِ وَ مَنْ بَلَغَ﴾ بر اين هم دلالت\n\nدارد كه رسالت آن حضرت عمومى و قرآنش ابدى و جهانى است، و از نظر دعوت به اسلام، هيچ فرقى بين كسانى كه قرآن را از خود او مى‏شنوند و بين كسانى كه از غير او مى‏شنوند نيست، و به عبارت ديگر آيه شريفه، دلالت مى‏كند بر اينكه قرآن كريم حجت ناطقى است از ناحيه خدا و كتابى است كه از روز نزولش تا قيام قيامت به نفع حق و عليه باطل، احتجاج مى‏كند.\n\nو اگر فرمود: تا شما را به وسيله آن انذار كنم، و نفرمود: به وسيله قرائت آن، براى اين بود كه قرآن بر هر كسى كه الفاظ آن را بشنود و معنايش را بفهمد و به مقاصدش پى ببرد و يا كسى برايش ترجمه و تفسير كند، و خلاصه بر هر كسى كه مضامين آن به گوشش بخورد حجت است، آرى، لازم نيست كتاب و نامه‏اى كه به سوى قومى ارسال مى‏شود حتما به زبان آن قوم باشد، بلكه شرط آن اين است كه اولا مضامينش شامل آنان شود و ثانيا حجت خود را بر آن قوم اقامه كند، هم چنان كه رسول خدا (صلى الله عليه وآله و سلم) به مردم مصر، حبشه، روم و ايران نامه‏ها نوشت و حال آنكه زبان آنان غير زبان قرآن بود، و همچنين عده‏اى از قبيل سلمان فارسى و بلال حبشى و صهيب رومى به آن جناب ايمان آوردند، و بسيارى از يهود با اينكه زبانشان عبرى بود به آن حضرت گرويدند. و اينها كه گفته شد روشن و غير قابل ترديد است.\n\n﴿أَ إِنَّكُمْ لَتَشْهَدُونَ أَنَّ مَعَ اَللَّهِ آلِهَةً أُخْرىَ قُلْ لاَ أَشْهَدُ...﴾\n\nپس از آنكه شهادت خداى را و اينكه خداوند بزرگترين گواه بر رسالت او است ذكر نمود و بيان كرد كه او جز به منظور دعوت به دين توحيد فرستاده نشده، و خاطرنشان ساخت كه بعد از شهادت خداى سبحان بر اينكه او را در الوهيت شريك نيست، ديگر انتظار نمى‏رود كسى بر تعدد آلهه شهادت دهد، اينك نبى محترم خود را دستور مى‏دهد كه از آنان به طور استعجاب و انكار بپرسد كه آيا باز هم به تعدد آلهه شهادت مى‏دهند؟ و اين معنا از بكار بردن حروف تاكيد «ان» و «لام» در مورد سؤال بخوبى استفاده مى‏شود، و گويا نفس نمى‏پذيرد كه بعد از اينكه ايشان شهادت پروردگار را شنيدند باز هم به خدايى خدايان ديگر شهادت دهند.\n\nسپس با جمله‏ ﴿قُلْ لاَ أَشْهَدُ﴾ دستور مى‏دهد كه با آنان در شهادت نابجايى كه داده‏اند مخالفت نموده، آن را از خود نفى نمايد. اين معنا از قرينه مقام استفاده مى‏شود. آن گاه مى‏فرمايد: ﴿قُلْ إِنَّمَا هُوَ إِلَهٌ وَاحِدٌ وَ إِنَّنِي بَرِي‏ءٌ مِمَّا تُشْرِكُونَ﴾ و اين همان شهادت بر وحدانيت خداى تعالى و برائت از شرك و شركائى است كه مشركين مدعى آن بودند.\n\n﴿اَلَّذِينَ آتَيْنَاهُمُ اَلْكِتَابَ يَعْرِفُونَهُ كَمَا يَعْرِفُونَ أَبْنَاءَهُمُ﴾ در اين فقره خبر مى‏دهد از شهادتى كه خداى سبحان در كتب آسمانى اهل كتاب بر نبوت خاتم الانبياء\n\n(صلى الله عليه وآله و سلم) داده و علماى آنان هم از آن شهادت اطلاع كافى دارند. زيرا كتبى كه از انبياء (علیه السلام) بر جاى مانده و مشتمل بر بشارتهاى پى در پى و غير قابل تشكيك در باره آمدن رسول خدا و اوصاف اوست هم اكنون نزد آنان موجود است.\n\nبنابراین علماى اهل كتاب به قدرى راجع به اوصاف آن حضرت استحضار دارند كه او را نديده مى‏شناسند، همانطورى كه بچه‏هاى خود را مى‏شناسند، و در جاى ديگر راجع به اين مطلب فرموده: ﴿اَلَّذِينَ يَتَّبِعُونَ اَلرَّسُولَ اَلنَّبِيَّ اَلْأُمِّيَّ اَلَّذِي يَجِدُونَهُ مَكْتُوباً عِنْدَهُمْ فِي اَلتَّوْرَاةِ وَ اَلْإِنْجِيلِ﴾ و نيز فرموده: ﴿مُحَمَّدٌ رَسُولُ اَللَّهِ وَ اَلَّذِينَ مَعَهُ أَشِدَّاءُ عَلَى اَلْكُفَّارِ رُحَمَاءُ بَيْنَهُمْ تَرَاهُمْ رُكَّعاً سُجَّداً يَبْتَغُونَ فَضْلاً مِنَ اَللَّهِ وَ رِضْوَاناً سِيمَاهُمْ فِي وُجُوهِهِمْ مِنْ أَثَرِ اَلسُّجُودِ ذَلِكَ مَثَلُهُمْ فِي اَلتَّوْرَاةِ وَ مَثَلُهُمْ فِي اَلْإِنْجِيلِ﴾ و نيز مى‏فرمايد: ﴿أَ وَ لَمْ يَكُنْ لَهُمْ آيَةً أَنْ يَعْلَمَهُ عُلَمَاءُ بَنِي إِسْرَائِيلَ﴾ و از آنجايى كه بعضى از علماى آنان بشاراتى را كه از اوصاف رسول خدا سراغ داشتند كتمان مى‏كردند، و از ايمان به او نيز استنكاف مى‏ورزيدند، لذا خداوند با جمله‏ ﴿اَلَّذِينَ خَسِرُوا أَنْفُسَهُمْ فَهُمْ لاَ يُؤْمِنُونَ﴾ خسران و زيانكارى آنان را بيان نمود.\n\nدر اينجا گفتار ما در تفسير آيه شريفه به پايان مى‏رسد. و البته در تفسير آيه «146» سوره بقره كه شباهت تامى با آيه مورد بحث ما دارد پاره‏اى مطالب را گذرانديم. از آن جمله وجه التفاتى را كه در آيه از حضور به غيبت به كار رفته بيان داشتيم، و به زودى در سوره اعراف نيز تتمه اين بحث خواهد آمد - ان شاء اللَه تعالى\n\n\n### بحث روايتى‏\n\nدر تفسير برهان از ابن بابويه نقل مى‏كند كه وى به سند خود از محمد بن عيسى بن\n\nعبيد روايت كرده كه گفت: حضرت ابى الحسن (علیه السلام) به من فرمود: اگر كسى از تو بپرسد كه آيا خداى عز و جل «شى‏ء» (چيز) است يا «لا شى‏ء»، چه جواب مى‏دهى؟ محمد مى‏گويد: عرض كردم: خداى عز و جل در كلام خود آنجا كه مى‏فرمايد: ﴿قُلْ أَيُّ شَيْ‏ءٍ أَكْبَرُ شَهَادَةً قُلِ اَللَّهُ شَهِيدٌ بَيْنِي وَ بَيْنَكُمْ﴾ شى‏ء بودن خود را اثبات كرده، چيزى كه هست در پاسخ از آن سؤال مى‏گويم: خداوند شى‏ء است ليكن نه مانند ساير اشياء زيرا اگر شيئيت را بكلى از او نفى كنم، در حقيقت وجودش را ابطال كرده‏ام، حضرت فرمود: احسنت، درست گفتى.\n\n\n#### بيان روايتى از امام رضا عليه السلام در باره سه مذهب و مسلك مردم در توحيد\n\nحضرت رضا (علیه السلام) فرمود: مردم را در توحيد سه مذهب است: 1 - نفى 2 - تشبيه 3 - اثبات به غير تشبيه.\n\n«مذهب نفى» غلط است، «مذهب تشبيه» يعنى او را به چيز ديگرى شبيه ساختن نيز غلط و باطل است، براى اينكه چيزى نيست كه شبيه خداى تبارك و تعالى باشد. بنابراین راه صحيح و ميانه همان «اثبات بدون تشبيه» است.\n\nمؤلف: مراد از «مذهب نفى»، نفى كردن معانى صفات است از خداوند، مانند حرفى كه معتزله در باره صفات بارى تعالى دارند، و در حكم آنست اينكه گفته شود صفات ثبوتيه چنين نيست كه در خداوند موجود باشد، بلكه معنايش در حقيقت نبود صفات ضد آن است مثلا معنى «قادر» و «عالم» اين است كه خداى تعالى عاجز و جاهل نيست و اين حرف همان نفى صفات است، مگر اينكه برگشت آن به همان مذهب سوم و غرض گوينده آن از: «عاجز نيست» اين باشد كه قدرت او مانند ساير قدرت‏ها نيست.\n\nو مراد از «مذهب تشبيه» اين است كه خداى تعالى با اينكه ﴿لَيْسَ كَمِثْلِهِ شَيْ‏ءٌ﴾ - چيزى شبيه او نيست به غير خودش تشبيه شود، يعنى از هر صفتى آن معناى محدودى كه در خود ما است و متمايز از ساير صفات است براى خدا اثبات و به وى نسبت داده شود، قدرتش مانند قدرت ما و علمش نظير علم ما و هم چنين ساير صفاتش مانند صفات ما باشد، و بطلان چنين مذهبى روشن است، براى اينكه اگر اوصافى كه خداى تعالى به آن متصف است مانند صفات ما باشد او نيز مانند ما محتاج خواهد بود، و با اين فرض ديگر واجب الوجود نخواهد بود - تعالى اللَه عن ذلك - و مراد از مذهب اثبات بدون تشبيه اين است كه از هر صفتى اصل آن در باره خداى\n\nتعالى اثبات و خصوصياتى كه آن صفت در ممكنات و مخلوقات به خود گرفته از حقتعالى نفى شود و به عبارت ديگر اصل صفت اثبات، و محدوديت آن به حدود امكانى نفى گردد.\n\n\n#### رواياتى در ذيل جمله: ﴿وَ مَنْ بَلَغَ﴾ و در باره معرفت اهل كتاب نسبت به پيامبر اسلام (صلى الله عليه وآله و سلم)\n\nدر تفسير قمى در روايت ابى الجارود است كه حضرت ابى جعفر (علیه السلام) در تفسير آيه‏ ﴿قُلْ أَيُّ شَيْ‏ءٍ أَكْبَرُ شَهَادَةً قُلِ اَللَّهُ شَهِيدٌ بَيْنِي وَ بَيْنَكُمْ﴾ فرمود: مشركين مكه در اوايل بعثت و همان موقعى كه رسول خدا (صلى الله عليه وآله و سلم) در مكه مى‏زيست به آن جناب گفتند: اى محمد آيا خداوند رسولى به غير تو نيافت كه به سوى ما گسيل دارد؟ گمان نمى‏كنيم كسى تو را در آنچه مى‏گويى تصديق كند، ما از يهود و نصارا هم راجع به تو پرسش كرديم آنها نيز اظهار بى اطلاعى كرده، گفتند: در كتبى كه نزد ما است ذكرى از اين مرد نشده، بنابراین، بايد گواهى بر رسالت خود بياورى. رسول خدا (صلى الله عليه وآله و سلم) فرمود: خدا بين من و شما گواه است.\n\nدر تفسير عياشى از بكير از محمد از ابى جعفر (علیه السلام) روايت شده كه در تفسير كلام خدا كه مى‏فرمايد: ﴿لِأُنْذِرَكُمْ بِهِ وَ مَنْ بَلَغَ﴾ فرمود: على (علیه السلام) از «من بلغ» است‏.\n\nمؤلف: ظاهر اين روايت اين است كه: «من بلغ» عطف بر ضمير «كم» است، و ظاهر آيه هم همين است، و ليكن در بعضى از روايات وارد شده كه مقصود از «من بلغ» تنها امام است، و لازمه آن اين است كه عطف بر فاعل مقدر در «لانذركم» بوده و معنايش اين باشد كه من و «من بلغ» - امام - شما را انذار كنيم.\n\nدر تفسير برهان است كه ابن بابويه به سند خود از يحيى بن عمران حلبى از پدرش از ابى عبد اللَه (علیه السلام) روايت كرده كه از آن جناب از معناى‏ ﴿وَ أُوحِيَ إِلَيَّ هَذَا اَلْقُرْآنُ لِأُنْذِرَكُمْ بِهِ وَ مَنْ بَلَغَ﴾ سؤال شد، و در جواب فرمود: يعنى اهل هر ملت و زبانى كه باشند.\n\nمؤلف: وجه اينكه چطور اين معنا از آيه استفاده مى‏شود گذشت.\n\nو در تفسير المنار است كه ابو الشيخ از ابى بن كعب روايت كرده كه گفت: اسيرانى را به حضور رسول خدا (صلى الله عليه وآله و سلم) آوردند، آن حضرت فرمود: آيا به اسلام دعوت شده‏ايد؟ گفتند نه، حضرت ايشان را رها كرده سپس اين آيه را تلاوت فرمودند: ﴿وَ أُوحِيَ إِلَيَّ\n\nهَذَا اَلْقُرْآنُ لِأُنْذِرَكُمْ بِهِ وَ مَنْ بَلَغَ﴾ آن گاه فرمود: اينان را رها كنيد تا به مامن و ديار خود باز گردند چون هنوز دعوت اسلام به گوششان نخورده است.\n\nو در تفسير قمى است كه عمر بن خطاب به عبد اللَه بن سلام گفت: آيا محمد را در كتب خود مى‏شناسيد؟ گفت آرى، به خدا سوگند او را به همان صفاتى كه خداوند در كتابهاى آسمانى ما، براى ما توصيف فرموده وقتى در بين شما او را ديديم شناختيم، همان طورى كه يكى از ما بچه خود را وقتى با بچه‏ها ببيند مى‏شناسد، و به آن خدايى كه من (ابن سلام) هميشه به ذات او سوگند مى‏خوردم هر آينه معرفتم به محمد بيشتر از معرفتى است كه به فرزندم دارم.\n\n"}